{
	"prefix": {
		"prov": "http://www.w3.org/ns/prov#",
		"rdt": "https://github.com/End-to-end-provenance/ExtendedProvJson/blob/master/JSON-format.md"
	},

	"agent" : {
		"rdt:a1": {
			"rdt:tool.name": "rdt",
			"rdt:tool.version": "3.3",
			"rdt:json.version": "2.3",
			"rdt:args.names": [
				"overwrite",
				"annotate.inside.functions",
				"first.loop",
				"max.loops",
				"snapshot.size",
				"save.debug"
			],
			"rdt:args.values": [
				"FALSE",
				"FALSE",
				"1",
				"0",
				"0",
				"FALSE"
			],
			"rdt:args.types": [
				"logical",
				"logical",
				"integer",
				"integer",
				"numeric",
				"logical"
			]
		}
	},

	"activity" : {
		"rdt:p1": {
			"rdt:name": "Console",
			"rdt:type": "Start",
			"rdt:elapsedTime": "0.706",
			"rdt:scriptNum": 1,
			"rdt:startLine": "NA",
			"rdt:startCol": "NA",
			"rdt:endLine": "NA",
			"rdt:endCol": "NA"
		},
		"rdt:p2": {
			"rdt:name": "library(modleR)",
			"rdt:type": "Operation",
			"rdt:elapsedTime": "1.816",
			"rdt:scriptNum": 1,
			"rdt:startLine": 1,
			"rdt:startCol": 1,
			"rdt:endLine": 1,
			"rdt:endCol": 15
		},
		"rdt:p3": {
			"rdt:name": "library(sp)",
			"rdt:type": "Operation",
			"rdt:elapsedTime": "0.079",
			"rdt:scriptNum": 1,
			"rdt:startLine": 2,
			"rdt:startCol": 1,
			"rdt:endLine": 2,
			"rdt:endCol": 11
		},
		"rdt:p4": {
			"rdt:name": "species <- names(example_occs)",
			"rdt:type": "Operation",
			"rdt:elapsedTime": "0.097",
			"rdt:scriptNum": 1,
			"rdt:startLine": 3,
			"rdt:startCol": 1,
			"rdt:endLine": 3,
			"rdt:endCol": 30
		},
		"rdt:p5": {
			"rdt:name": "occs <- example_occs[[1]]",
			"rdt:type": "Operation",
			"rdt:elapsedTime": "0.053",
			"rdt:scriptNum": 1,
			"rdt:startLine": 4,
			"rdt:startCol": 1,
			"rdt:endLine": 4,
			"rdt:endCol": 25
		},
		"rdt:p6": {
			"rdt:name": "test_folder <- \"~/Dropbox/Reproducibility/prov2repr/prov_sam",
			"rdt:type": "Operation",
			"rdt:elapsedTime": "0.17",
			"rdt:scriptNum": 1,
			"rdt:startLine": 5,
			"rdt:startCol": 1,
			"rdt:endLine": 5,
			"rdt:endCol": 80
		},
		"rdt:p7": {
			"rdt:name": "sdmdata_1sp <- modleR::setup_sdmdata(species_name = species[",
			"rdt:type": "Operation",
			"rdt:elapsedTime": "4.25",
			"rdt:scriptNum": 1,
			"rdt:startLine": 6,
			"rdt:startCol": 1,
			"rdt:endLine": 11,
			"rdt:endCol": 67
		},
		"rdt:p8": {
			"rdt:name": "many <- modleR::do_many(species_name = species[1], predictor",
			"rdt:type": "Operation",
			"rdt:elapsedTime": "20.379",
			"rdt:scriptNum": 1,
			"rdt:startLine": 12,
			"rdt:startCol": 1,
			"rdt:endLine": 16,
			"rdt:endCol": 32
		},
		"rdt:p9": {
			"rdt:name": "fm <- modleR::final_model(species_name = species[1], algorit",
			"rdt:type": "Operation",
			"rdt:elapsedTime": "14.134",
			"rdt:scriptNum": 1,
			"rdt:startLine": 17,
			"rdt:startCol": 1,
			"rdt:endLine": 20,
			"rdt:endCol": 36
		},
		"rdt:p10": {
			"rdt:name": "ens <- modleR::ensemble_model(species_name = species[1], occ",
			"rdt:type": "Operation",
			"rdt:elapsedTime": "9.55",
			"rdt:scriptNum": 1,
			"rdt:startLine": 21,
			"rdt:startCol": 1,
			"rdt:endLine": 25,
			"rdt:endCol": 65
		},
		"rdt:p11": {
			"rdt:name": "Console",
			"rdt:type": "Finish",
			"rdt:elapsedTime": "0.757",
			"rdt:scriptNum": 1,
			"rdt:startLine": "NA",
			"rdt:startCol": "NA",
			"rdt:endLine": "NA",
			"rdt:endCol": "NA"
		}
	},

	"entity" : {
		"rdt:d1": {
			"rdt:name": "species",
			"rdt:value": "data/1-species.txt",
			"rdt:valType": "{\"container\":\"vector\", \"dimension\":[4], \"type\":[\"character\"]}",
			"rdt:type": "Snapshot",
			"rdt:scope": "R_GlobalEnv",
			"rdt:fromEnv": false,
			"rdt:hash": "",
			"rdt:timestamp": "2021-01-12T13.31.27-03",
			"rdt:location": ""
		},
		"rdt:d2": {
			"rdt:name": "occs",
			"rdt:value": "data/2-occs.csv",
			"rdt:valType": "{\"container\":\"data_frame\", \"dimension\":[104,3], \"type\":[\"character\",\"numeric\",\"numeric\"]}",
			"rdt:type": "Snapshot",
			"rdt:scope": "R_GlobalEnv",
			"rdt:fromEnv": false,
			"rdt:hash": "",
			"rdt:timestamp": "2021-01-12T13.31.27-03",
			"rdt:location": ""
		},
		"rdt:d3": {
			"rdt:name": "test_folder",
			"rdt:value": "\"~/Dropbox/Reproducibility/prov2repr/prov_samples/modler_results\"",
			"rdt:valType": "{\"container\":\"vector\", \"dimension\":[1], \"type\":[\"character\"]}",
			"rdt:type": "Data",
			"rdt:scope": "R_GlobalEnv",
			"rdt:fromEnv": false,
			"rdt:hash": "",
			"rdt:timestamp": "",
			"rdt:location": ""
		},
		"rdt:d4": {
			"rdt:name": "package.rds",
			"rdt:value": "data/4-package.rds",
			"rdt:valType": "{\"container\":\"vector\", \"dimension\":[1], \"type\":[\"character\"]}",
			"rdt:type": "File",
			"rdt:scope": "undefined",
			"rdt:fromEnv": false,
			"rdt:hash": "0f28b070a556ad4a7771fc28980eba46",
			"rdt:timestamp": "2020-06-23T09.11.46-03",
			"rdt:location": "/usr/lib/R/library/base/Meta/package.rds"
		},
		"rdt:d5": {
			"rdt:name": "package.rds",
			"rdt:value": "data/5-package.rds",
			"rdt:valType": "{\"container\":\"vector\", \"dimension\":[1], \"type\":[\"character\"]}",
			"rdt:type": "File",
			"rdt:scope": "undefined",
			"rdt:fromEnv": false,
			"rdt:hash": "a4c4e97dd429d1b394301305adf517c0",
			"rdt:timestamp": "2020-07-06T20.52.28-03",
			"rdt:location": "/home/mondelli/R/x86_64-pc-linux-gnu-library/4.0/Rcpp/Meta/package.rds"
		},
		"rdt:d6": {
			"rdt:name": "package.rds",
			"rdt:value": "data/6-package.rds",
			"rdt:valType": "{\"container\":\"vector\", \"dimension\":[1], \"type\":[\"character\"]}",
			"rdt:type": "File",
			"rdt:scope": "undefined",
			"rdt:fromEnv": false,
			"rdt:hash": "9e1a45981ebb836da84eaf5468580ba8",
			"rdt:timestamp": "2020-11-03T17.15.06-03",
			"rdt:location": "/home/mondelli/R/x86_64-pc-linux-gnu-library/4.0/modleR/Meta/package.rds"
		},
		"rdt:d7": {
			"rdt:name": "package.rds",
			"rdt:value": "data/7-package.rds",
			"rdt:valType": "{\"container\":\"vector\", \"dimension\":[1], \"type\":[\"character\"]}",
			"rdt:type": "File",
			"rdt:scope": "undefined",
			"rdt:fromEnv": false,
			"rdt:hash": "bc4ed03fe691f3b47b5b57747b3b8fce",
			"rdt:timestamp": "2020-11-24T17.46.21-03",
			"rdt:location": "/home/mondelli/R/x86_64-pc-linux-gnu-library/4.0/pillar/Meta/package.rds"
		},
		"rdt:d8": {
			"rdt:name": "package.rds",
			"rdt:value": "data/8-package.rds",
			"rdt:valType": "{\"container\":\"vector\", \"dimension\":[1], \"type\":[\"character\"]}",
			"rdt:type": "File",
			"rdt:scope": "undefined",
			"rdt:fromEnv": false,
			"rdt:hash": "9b67d569a63bf8327cca1ad9884b09d5",
			"rdt:timestamp": "2020-06-23T09.11.46-03",
			"rdt:location": "/usr/lib/R/library/compiler/Meta/package.rds"
		},
		"rdt:d9": {
			"rdt:name": "package.rds",
			"rdt:value": "data/9-package.rds",
			"rdt:valType": "{\"container\":\"vector\", \"dimension\":[1], \"type\":[\"character\"]}",
			"rdt:type": "File",
			"rdt:scope": "undefined",
			"rdt:fromEnv": false,
			"rdt:hash": "4b26da284776b0cd1aa6f7ff8b520ad5",
			"rdt:timestamp": "2020-06-23T09.11.46-03",
			"rdt:location": "/usr/lib/R/library/methods/Meta/package.rds"
		},
		"rdt:d10": {
			"rdt:name": "package.rds",
			"rdt:value": "data/10-package.rds",
			"rdt:valType": "{\"container\":\"vector\", \"dimension\":[1], \"type\":[\"character\"]}",
			"rdt:type": "File",
			"rdt:scope": "undefined",
			"rdt:fromEnv": false,
			"rdt:hash": "64d890307d0e32d52b352b1354858c4d",
			"rdt:timestamp": "2020-06-23T09.11.46-03",
			"rdt:location": "/usr/lib/R/library/utils/Meta/package.rds"
		},
		"rdt:d11": {
			"rdt:name": "package.rds",
			"rdt:value": "data/11-package.rds",
			"rdt:valType": "{\"container\":\"vector\", \"dimension\":[1], \"type\":[\"character\"]}",
			"rdt:type": "File",
			"rdt:scope": "undefined",
			"rdt:fromEnv": false,
			"rdt:hash": "52637d1cdf05878923dbf5bfa19f4670",
			"rdt:timestamp": "2020-06-23T09.11.46-03",
			"rdt:location": "/usr/lib/R/library/tools/Meta/package.rds"
		},
		"rdt:d12": {
			"rdt:name": "package.rds",
			"rdt:value": "data/12-package.rds",
			"rdt:valType": "{\"container\":\"vector\", \"dimension\":[1], \"type\":[\"character\"]}",
			"rdt:type": "File",
			"rdt:scope": "undefined",
			"rdt:fromEnv": false,
			"rdt:hash": "068d83b2e2f31447adc1e6b612ba38e9",
			"rdt:timestamp": "2020-06-23T09.11.46-03",
			"rdt:location": "/usr/lib/R/library/grDevices/Meta/package.rds"
		},
		"rdt:d13": {
			"rdt:name": "package.rds",
			"rdt:value": "data/13-package.rds",
			"rdt:valType": "{\"container\":\"vector\", \"dimension\":[1], \"type\":[\"character\"]}",
			"rdt:type": "File",
			"rdt:scope": "undefined",
			"rdt:fromEnv": false,
			"rdt:hash": "7204fc6f994734b27fee229115051567",
			"rdt:timestamp": "2020-07-06T19.43.07-03",
			"rdt:location": "/home/mondelli/R/x86_64-pc-linux-gnu-library/4.0/lattice/Meta/package.rds"
		},
		"rdt:d14": {
			"rdt:name": "package.rds",
			"rdt:value": "data/14-package.rds",
			"rdt:valType": "{\"container\":\"vector\", \"dimension\":[1], \"type\":[\"character\"]}",
			"rdt:type": "File",
			"rdt:scope": "undefined",
			"rdt:fromEnv": false,
			"rdt:hash": "2ae9245606711ff03e13eb33094f60c7",
			"rdt:timestamp": "2020-12-16T20.12.32-03",
			"rdt:location": "/home/mondelli/R/x86_64-pc-linux-gnu-library/4.0/jsonlite/Meta/package.rds"
		},
		"rdt:d15": {
			"rdt:name": "package.rds",
			"rdt:value": "data/15-package.rds",
			"rdt:valType": "{\"container\":\"vector\", \"dimension\":[1], \"type\":[\"character\"]}",
			"rdt:type": "File",
			"rdt:scope": "undefined",
			"rdt:fromEnv": false,
			"rdt:hash": "87cfe7bb5144664b589f266301d8acdb",
			"rdt:timestamp": "2020-07-06T20.07.54-03",
			"rdt:location": "/home/mondelli/R/x86_64-pc-linux-gnu-library/4.0/lifecycle/Meta/package.rds"
		},
		"rdt:d16": {
			"rdt:name": "package.rds",
			"rdt:value": "data/16-package.rds",
			"rdt:valType": "{\"container\":\"vector\", \"dimension\":[1], \"type\":[\"character\"]}",
			"rdt:type": "File",
			"rdt:scope": "undefined",
			"rdt:fromEnv": false,
			"rdt:hash": "246c2b6dbb6e573ec2223dee88dc3ec7",
			"rdt:timestamp": "2020-11-03T17.06.16-03",
			"rdt:location": "/home/mondelli/R/x86_64-pc-linux-gnu-library/4.0/tibble/Meta/package.rds"
		},
		"rdt:d17": {
			"rdt:name": "package.rds",
			"rdt:value": "data/17-package.rds",
			"rdt:valType": "{\"container\":\"vector\", \"dimension\":[1], \"type\":[\"character\"]}",
			"rdt:type": "File",
			"rdt:scope": "undefined",
			"rdt:fromEnv": false,
			"rdt:hash": "439573aa78033a0e39f72e873ebd771c",
			"rdt:timestamp": "2020-07-06T19.58.47-03",
			"rdt:location": "/home/mondelli/R/x86_64-pc-linux-gnu-library/4.0/gtable/Meta/package.rds"
		},
		"rdt:d18": {
			"rdt:name": "package.rds",
			"rdt:value": "data/18-package.rds",
			"rdt:valType": "{\"container\":\"vector\", \"dimension\":[1], \"type\":[\"character\"]}",
			"rdt:type": "File",
			"rdt:scope": "undefined",
			"rdt:fromEnv": false,
			"rdt:hash": "8e20a6c37253adda62c6305211f066f7",
			"rdt:timestamp": "2020-07-06T19.59.43-03",
			"rdt:location": "/home/mondelli/R/x86_64-pc-linux-gnu-library/4.0/pkgconfig/Meta/package.rds"
		},
		"rdt:d19": {
			"rdt:name": "package.rds",
			"rdt:value": "data/19-package.rds",
			"rdt:valType": "{\"container\":\"vector\", \"dimension\":[1], \"type\":[\"character\"]}",
			"rdt:type": "File",
			"rdt:scope": "undefined",
			"rdt:fromEnv": false,
			"rdt:hash": "702f07b7c7584e886f4bdb24e5924a83",
			"rdt:timestamp": "2021-01-04T14.34.51-03",
			"rdt:location": "/home/mondelli/R/x86_64-pc-linux-gnu-library/4.0/rlang/Meta/package.rds"
		},
		"rdt:d20": {
			"rdt:name": "package.rds",
			"rdt:value": "data/20-package.rds",
			"rdt:valType": "{\"container\":\"vector\", \"dimension\":[1], \"type\":[\"character\"]}",
			"rdt:type": "File",
			"rdt:scope": "undefined",
			"rdt:fromEnv": false,
			"rdt:hash": "5a56668306a4ac4b4a3ad3f3c9703ece",
			"rdt:timestamp": "2020-11-24T17.45.34-03",
			"rdt:location": "/home/mondelli/R/x86_64-pc-linux-gnu-library/4.0/cli/Meta/package.rds"
		},
		"rdt:d21": {
			"rdt:name": "package.rds",
			"rdt:value": "data/21-package.rds",
			"rdt:valType": "{\"container\":\"vector\", \"dimension\":[1], \"type\":[\"character\"]}",
			"rdt:type": "File",
			"rdt:scope": "undefined",
			"rdt:fromEnv": false,
			"rdt:hash": "183212b91060b6e77c5103094062bdef",
			"rdt:timestamp": "2020-11-24T17.45.38-03",
			"rdt:location": "/home/mondelli/R/x86_64-pc-linux-gnu-library/4.0/rstudioapi/Meta/package.rds"
		},
		"rdt:d22": {
			"rdt:name": "package.rds",
			"rdt:value": "data/22-package.rds",
			"rdt:valType": "{\"container\":\"vector\", \"dimension\":[1], \"type\":[\"character\"]}",
			"rdt:type": "File",
			"rdt:scope": "undefined",
			"rdt:fromEnv": false,
			"rdt:hash": "9f5130bbf471524c669807d0681602eb",
			"rdt:timestamp": "2020-07-06T20.02.19-03",
			"rdt:location": "/home/mondelli/R/x86_64-pc-linux-gnu-library/4.0/curl/Meta/package.rds"
		},
		"rdt:d23": {
			"rdt:name": "package.rds",
			"rdt:value": "data/23-package.rds",
			"rdt:valType": "{\"container\":\"vector\", \"dimension\":[1], \"type\":[\"character\"]}",
			"rdt:type": "File",
			"rdt:scope": "undefined",
			"rdt:fromEnv": false,
			"rdt:hash": "7a9c177825365befd3043560176eceeb",
			"rdt:timestamp": "2020-11-03T17.14.16-03",
			"rdt:location": "/home/mondelli/R/x86_64-pc-linux-gnu-library/4.0/kuenm/Meta/package.rds"
		},
		"rdt:d24": {
			"rdt:name": "package.rds",
			"rdt:value": "data/24-package.rds",
			"rdt:valType": "{\"container\":\"vector\", \"dimension\":[1], \"type\":[\"character\"]}",
			"rdt:type": "File",
			"rdt:scope": "undefined",
			"rdt:fromEnv": false,
			"rdt:hash": "16286845115b33c42e7803fc0701106c",
			"rdt:timestamp": "2021-01-07T18.36.29-03",
			"rdt:location": "/home/mondelli/R/x86_64-pc-linux-gnu-library/4.0/xfun/Meta/package.rds"
		},
		"rdt:d25": {
			"rdt:name": "package.rds",
			"rdt:value": "data/25-package.rds",
			"rdt:valType": "{\"container\":\"vector\", \"dimension\":[1], \"type\":[\"character\"]}",
			"rdt:type": "File",
			"rdt:scope": "undefined",
			"rdt:fromEnv": false,
			"rdt:hash": "bff8bedc089983afb942ee8049cd08b1",
			"rdt:timestamp": "2020-07-06T20.12.53-03",
			"rdt:location": "/home/mondelli/R/x86_64-pc-linux-gnu-library/4.0/dismo/Meta/package.rds"
		},
		"rdt:d26": {
			"rdt:name": "package.rds",
			"rdt:value": "data/26-package.rds",
			"rdt:valType": "{\"container\":\"vector\", \"dimension\":[1], \"type\":[\"character\"]}",
			"rdt:type": "File",
			"rdt:scope": "undefined",
			"rdt:fromEnv": false,
			"rdt:hash": "275f53b32daf0a373fa6bf45707af379",
			"rdt:timestamp": "2020-10-05T15.08.17-03",
			"rdt:location": "/home/mondelli/R/x86_64-pc-linux-gnu-library/4.0/raster/Meta/package.rds"
		},
		"rdt:d27": {
			"rdt:name": "package.rds",
			"rdt:value": "data/27-package.rds",
			"rdt:valType": "{\"container\":\"vector\", \"dimension\":[1], \"type\":[\"character\"]}",
			"rdt:type": "File",
			"rdt:scope": "undefined",
			"rdt:fromEnv": false,
			"rdt:hash": "1c95de0cd9e514f1c8562eff3f2cbd0a",
			"rdt:timestamp": "2020-10-01T16.03.01-03",
			"rdt:location": "/home/mondelli/R/x86_64-pc-linux-gnu-library/4.0/withr/Meta/package.rds"
		},
		"rdt:d28": {
			"rdt:name": "package.rds",
			"rdt:value": "data/28-package.rds",
			"rdt:valType": "{\"container\":\"vector\", \"dimension\":[1], \"type\":[\"character\"]}",
			"rdt:type": "File",
			"rdt:scope": "undefined",
			"rdt:fromEnv": false,
			"rdt:hash": "55d77b51988974b77e3377e692fa247a",
			"rdt:timestamp": "2021-01-12T12.33.00-03",
			"rdt:location": "/home/mondelli/R/x86_64-pc-linux-gnu-library/4.0/rdt2repr/Meta/package.rds"
		},
		"rdt:d29": {
			"rdt:name": "package.rds",
			"rdt:value": "data/29-package.rds",
			"rdt:valType": "{\"container\":\"vector\", \"dimension\":[1], \"type\":[\"character\"]}",
			"rdt:type": "File",
			"rdt:scope": "undefined",
			"rdt:fromEnv": false,
			"rdt:hash": "4f11a94d989eb9db8f52c766701137d6",
			"rdt:timestamp": "2020-08-24T13.59.35-03",
			"rdt:location": "/home/mondelli/R/x86_64-pc-linux-gnu-library/4.0/dplyr/Meta/package.rds"
		},
		"rdt:d30": {
			"rdt:name": "package.rds",
			"rdt:value": "data/30-package.rds",
			"rdt:valType": "{\"container\":\"vector\", \"dimension\":[1], \"type\":[\"character\"]}",
			"rdt:type": "File",
			"rdt:scope": "undefined",
			"rdt:fromEnv": false,
			"rdt:hash": "ed9fa2990a4ae4c524efd1f9a6ce1ab5",
			"rdt:timestamp": "2020-07-06T20.20.52-03",
			"rdt:location": "/home/mondelli/R/x86_64-pc-linux-gnu-library/4.0/provParseR/Meta/package.rds"
		},
		"rdt:d31": {
			"rdt:name": "package.rds",
			"rdt:value": "data/31-package.rds",
			"rdt:valType": "{\"container\":\"vector\", \"dimension\":[1], \"type\":[\"character\"]}",
			"rdt:type": "File",
			"rdt:scope": "undefined",
			"rdt:fromEnv": false,
			"rdt:hash": "a32ac81e7244becc509493f7fe0c3364",
			"rdt:timestamp": "2020-07-06T20.07.52-03",
			"rdt:location": "/home/mondelli/R/x86_64-pc-linux-gnu-library/4.0/stringr/Meta/package.rds"
		},
		"rdt:d32": {
			"rdt:name": "package.rds",
			"rdt:value": "data/32-package.rds",
			"rdt:valType": "{\"container\":\"vector\", \"dimension\":[1], \"type\":[\"character\"]}",
			"rdt:type": "File",
			"rdt:scope": "undefined",
			"rdt:fromEnv": false,
			"rdt:hash": "f3b936c5aa3c5d71d3dad634ea524d99",
			"rdt:timestamp": "2020-11-11T13.56.00-03",
			"rdt:location": "/home/mondelli/R/x86_64-pc-linux-gnu-library/4.0/rdflib/Meta/package.rds"
		},
		"rdt:d33": {
			"rdt:name": "package.rds",
			"rdt:value": "data/33-package.rds",
			"rdt:valType": "{\"container\":\"vector\", \"dimension\":[1], \"type\":[\"character\"]}",
			"rdt:type": "File",
			"rdt:scope": "undefined",
			"rdt:fromEnv": false,
			"rdt:hash": "013dc0dd6ef98176fe8739721993d62d",
			"rdt:timestamp": "2020-12-23T22.45.29-03",
			"rdt:location": "/home/mondelli/R/x86_64-pc-linux-gnu-library/4.0/roxygen2/Meta/package.rds"
		},
		"rdt:d34": {
			"rdt:name": "package.rds",
			"rdt:value": "data/34-package.rds",
			"rdt:valType": "{\"container\":\"vector\", \"dimension\":[1], \"type\":[\"character\"]}",
			"rdt:type": "File",
			"rdt:scope": "undefined",
			"rdt:fromEnv": false,
			"rdt:hash": "b966ec36fa3717261fdef1e023a0377e",
			"rdt:timestamp": "2020-10-01T16.04.22-03",
			"rdt:location": "/home/mondelli/R/x86_64-pc-linux-gnu-library/4.0/knitr/Meta/package.rds"
		},
		"rdt:d35": {
			"rdt:name": "package.rds",
			"rdt:value": "data/35-package.rds",
			"rdt:valType": "{\"container\":\"vector\", \"dimension\":[1], \"type\":[\"character\"]}",
			"rdt:type": "File",
			"rdt:scope": "undefined",
			"rdt:fromEnv": false,
			"rdt:hash": "47c75ecb252860cfbbc5ee77e61d44fc",
			"rdt:timestamp": "2020-07-06T20.05.04-03",
			"rdt:location": "/home/mondelli/R/x86_64-pc-linux-gnu-library/4.0/xml2/Meta/package.rds"
		},
		"rdt:d36": {
			"rdt:name": "package.rds",
			"rdt:value": "data/36-package.rds",
			"rdt:valType": "{\"container\":\"vector\", \"dimension\":[1], \"type\":[\"character\"]}",
			"rdt:type": "File",
			"rdt:scope": "undefined",
			"rdt:fromEnv": false,
			"rdt:hash": "b3604dac30baf4b4b8c27b5698ec7e57",
			"rdt:timestamp": "2020-10-01T16.01.07-03",
			"rdt:location": "/home/mondelli/R/x86_64-pc-linux-gnu-library/4.0/rgeos/Meta/package.rds"
		},
		"rdt:d37": {
			"rdt:name": "package.rds",
			"rdt:value": "data/37-package.rds",
			"rdt:valType": "{\"container\":\"vector\", \"dimension\":[1], \"type\":[\"character\"]}",
			"rdt:type": "File",
			"rdt:scope": "undefined",
			"rdt:fromEnv": false,
			"rdt:hash": "6a291736b7eb64211339df8043c220df",
			"rdt:timestamp": "2020-11-03T17.04.59-03",
			"rdt:location": "/home/mondelli/R/x86_64-pc-linux-gnu-library/4.0/generics/Meta/package.rds"
		},
		"rdt:d38": {
			"rdt:name": "package.rds",
			"rdt:value": "data/38-package.rds",
			"rdt:valType": "{\"container\":\"vector\", \"dimension\":[1], \"type\":[\"character\"]}",
			"rdt:type": "File",
			"rdt:scope": "undefined",
			"rdt:fromEnv": false,
			"rdt:hash": "6f4263b3eb3fbcad113118de9112cf9b",
			"rdt:timestamp": "2020-12-23T21.26.53-03",
			"rdt:location": "/home/mondelli/R/x86_64-pc-linux-gnu-library/4.0/vctrs/Meta/package.rds"
		},
		"rdt:d39": {
			"rdt:name": "package.rds",
			"rdt:value": "data/39-package.rds",
			"rdt:valType": "{\"container\":\"vector\", \"dimension\":[1], \"type\":[\"character\"]}",
			"rdt:type": "File",
			"rdt:scope": "undefined",
			"rdt:fromEnv": false,
			"rdt:hash": "64e8172aadb96a930693f3e4efe9db47",
			"rdt:timestamp": "2020-06-23T09.11.46-03",
			"rdt:location": "/usr/lib/R/library/graphics/Meta/package.rds"
		},
		"rdt:d40": {
			"rdt:name": "package.rds",
			"rdt:value": "data/40-package.rds",
			"rdt:valType": "{\"container\":\"vector\", \"dimension\":[1], \"type\":[\"character\"]}",
			"rdt:type": "File",
			"rdt:scope": "undefined",
			"rdt:fromEnv": false,
			"rdt:hash": "00f6ad05b87d72d385bfa8544fc1a212",
			"rdt:timestamp": "2020-07-06T19.47.24-03",
			"rdt:location": "/home/mondelli/R/x86_64-pc-linux-gnu-library/4.0/gtools/Meta/package.rds"
		},
		"rdt:d41": {
			"rdt:name": "package.rds",
			"rdt:value": "data/41-package.rds",
			"rdt:valType": "{\"container\":\"vector\", \"dimension\":[1], \"type\":[\"character\"]}",
			"rdt:type": "File",
			"rdt:scope": "undefined",
			"rdt:fromEnv": false,
			"rdt:hash": "03d96be6ef83769210d80e27be516a2d",
			"rdt:timestamp": "2020-06-23T09.11.46-03",
			"rdt:location": "/usr/lib/R/library/datasets/Meta/package.rds"
		},
		"rdt:d42": {
			"rdt:name": "package.rds",
			"rdt:value": "data/42-package.rds",
			"rdt:valType": "{\"container\":\"vector\", \"dimension\":[1], \"type\":[\"character\"]}",
			"rdt:type": "File",
			"rdt:scope": "undefined",
			"rdt:fromEnv": false,
			"rdt:hash": "bf32ef2cb6e239d9295b8940e7b84e9b",
			"rdt:timestamp": "2020-06-23T09.11.46-03",
			"rdt:location": "/usr/lib/R/library/stats/Meta/package.rds"
		},
		"rdt:d43": {
			"rdt:name": "package.rds",
			"rdt:value": "data/43-package.rds",
			"rdt:valType": "{\"container\":\"vector\", \"dimension\":[1], \"type\":[\"character\"]}",
			"rdt:type": "File",
			"rdt:scope": "undefined",
			"rdt:fromEnv": false,
			"rdt:hash": "a5968a0cb0976ac859f2a2876b2cd2a2",
			"rdt:timestamp": "2020-07-09T16.47.20-03",
			"rdt:location": "/home/mondelli/R/x86_64-pc-linux-gnu-library/4.0/hms/Meta/package.rds"
		},
		"rdt:d44": {
			"rdt:name": "package.rds",
			"rdt:value": "data/44-package.rds",
			"rdt:valType": "{\"container\":\"vector\", \"dimension\":[1], \"type\":[\"character\"]}",
			"rdt:type": "File",
			"rdt:scope": "undefined",
			"rdt:fromEnv": false,
			"rdt:hash": "dcc70f5567a2f247684c1e0f3dc077c8",
			"rdt:timestamp": "2020-11-03T17.14.43-03",
			"rdt:location": "/home/mondelli/R/x86_64-pc-linux-gnu-library/4.0/maxnet/Meta/package.rds"
		},
		"rdt:d45": {
			"rdt:name": "package.rds",
			"rdt:value": "data/45-package.rds",
			"rdt:valType": "{\"container\":\"vector\", \"dimension\":[1], \"type\":[\"character\"]}",
			"rdt:type": "File",
			"rdt:scope": "undefined",
			"rdt:fromEnv": false,
			"rdt:hash": "876c6311b51a4c883813d4be2036df21",
			"rdt:timestamp": "2020-07-06T20.05.16-03",
			"rdt:location": "/home/mondelli/R/x86_64-pc-linux-gnu-library/4.0/gbRd/Meta/package.rds"
		},
		"rdt:d46": {
			"rdt:name": "package.rds",
			"rdt:value": "data/46-package.rds",
			"rdt:valType": "{\"container\":\"vector\", \"dimension\":[1], \"type\":[\"character\"]}",
			"rdt:type": "File",
			"rdt:scope": "undefined",
			"rdt:fromEnv": false,
			"rdt:hash": "d336655e6388ed77cba73a4c55c05ea6",
			"rdt:timestamp": "2020-11-11T13.55.45-03",
			"rdt:location": "/home/mondelli/R/x86_64-pc-linux-gnu-library/4.0/jsonld/Meta/package.rds"
		},
		"rdt:d47": {
			"rdt:name": "package.rds",
			"rdt:value": "data/47-package.rds",
			"rdt:valType": "{\"container\":\"vector\", \"dimension\":[1], \"type\":[\"character\"]}",
			"rdt:type": "File",
			"rdt:scope": "undefined",
			"rdt:fromEnv": false,
			"rdt:hash": "48eac5362c075fc859d730bc6d5f40c0",
			"rdt:timestamp": "2020-11-11T13.55.50-03",
			"rdt:location": "/home/mondelli/R/x86_64-pc-linux-gnu-library/4.0/redland/Meta/package.rds"
		},
		"rdt:d48": {
			"rdt:name": "package.rds",
			"rdt:value": "data/48-package.rds",
			"rdt:valType": "{\"container\":\"vector\", \"dimension\":[1], \"type\":[\"character\"]}",
			"rdt:type": "File",
			"rdt:scope": "undefined",
			"rdt:fromEnv": false,
			"rdt:hash": "9689523e39f8b13e6762b48e3c1f8eae",
			"rdt:timestamp": "2020-06-23T09.11.46-03",
			"rdt:location": "/usr/lib/R/library/grid/Meta/package.rds"
		},
		"rdt:d49": {
			"rdt:name": "package.rds",
			"rdt:value": "data/49-package.rds",
			"rdt:valType": "{\"container\":\"vector\", \"dimension\":[1], \"type\":[\"character\"]}",
			"rdt:type": "File",
			"rdt:scope": "undefined",
			"rdt:fromEnv": false,
			"rdt:hash": "84ecb04f6bdf8c5c1df7cef4546c40d0",
			"rdt:timestamp": "2020-07-06T19.52.19-03",
			"rdt:location": "/home/mondelli/R/x86_64-pc-linux-gnu-library/4.0/tidyselect/Meta/package.rds"
		},
		"rdt:d50": {
			"rdt:name": "package.rds",
			"rdt:value": "data/50-package.rds",
			"rdt:valType": "{\"container\":\"vector\", \"dimension\":[1], \"type\":[\"character\"]}",
			"rdt:type": "File",
			"rdt:scope": "undefined",
			"rdt:fromEnv": false,
			"rdt:hash": "3ab01d258c090c0c24048520b1f7d116",
			"rdt:timestamp": "2020-10-01T15.57.49-03",
			"rdt:location": "/home/mondelli/R/x86_64-pc-linux-gnu-library/4.0/glue/Meta/package.rds"
		},
		"rdt:d51": {
			"rdt:name": "package.rds",
			"rdt:value": "data/51-package.rds",
			"rdt:valType": "{\"container\":\"vector\", \"dimension\":[1], \"type\":[\"character\"]}",
			"rdt:type": "File",
			"rdt:scope": "undefined",
			"rdt:fromEnv": false,
			"rdt:hash": "68838a61fafc8b6be5dd94266913f5c2",
			"rdt:timestamp": "2020-11-03T17.04.58-03",
			"rdt:location": "/home/mondelli/R/x86_64-pc-linux-gnu-library/4.0/R6/Meta/package.rds"
		},
		"rdt:d52": {
			"rdt:name": "package.rds",
			"rdt:value": "data/52-package.rds",
			"rdt:valType": "{\"container\":\"vector\", \"dimension\":[1], \"type\":[\"character\"]}",
			"rdt:type": "File",
			"rdt:scope": "undefined",
			"rdt:fromEnv": false,
			"rdt:hash": "6e2ac1824f3293e763adebe7cdb8198d",
			"rdt:timestamp": "2020-07-06T19.59.36-03",
			"rdt:location": "/home/mondelli/R/x86_64-pc-linux-gnu-library/4.0/fansi/Meta/package.rds"
		},
		"rdt:d53": {
			"rdt:name": "package.rds",
			"rdt:value": "data/53-package.rds",
			"rdt:valType": "{\"container\":\"vector\", \"dimension\":[1], \"type\":[\"character\"]}",
			"rdt:type": "File",
			"rdt:scope": "undefined",
			"rdt:fromEnv": false,
			"rdt:hash": "9af692352b7d07b0bfb0758c21921a30",
			"rdt:timestamp": "2020-11-03T17.12.06-03",
			"rdt:location": "/home/mondelli/R/x86_64-pc-linux-gnu-library/4.0/Rdpack/Meta/package.rds"
		},
		"rdt:d54": {
			"rdt:name": "package.rds",
			"rdt:value": "data/54-package.rds",
			"rdt:valType": "{\"container\":\"vector\", \"dimension\":[1], \"type\":[\"character\"]}",
			"rdt:type": "File",
			"rdt:scope": "undefined",
			"rdt:fromEnv": false,
			"rdt:hash": "fe11ae7ff16bc3d343630ac4f462d874",
			"rdt:timestamp": "2020-07-06T20.13.11-03",
			"rdt:location": "/home/mondelli/R/x86_64-pc-linux-gnu-library/4.0/sessioninfo/Meta/package.rds"
		},
		"rdt:d55": {
			"rdt:name": "package.rds",
			"rdt:value": "data/55-package.rds",
			"rdt:valType": "{\"container\":\"vector\", \"dimension\":[1], \"type\":[\"character\"]}",
			"rdt:type": "File",
			"rdt:scope": "undefined",
			"rdt:fromEnv": false,
			"rdt:hash": "f2fde04f9e9ad3d8ed808ada20a1edc0",
			"rdt:timestamp": "2020-11-03T17.04.25-03",
			"rdt:location": "/home/mondelli/R/x86_64-pc-linux-gnu-library/4.0/sp/Meta/package.rds"
		},
		"rdt:d56": {
			"rdt:name": "package.rds",
			"rdt:value": "data/56-package.rds",
			"rdt:valType": "{\"container\":\"vector\", \"dimension\":[1], \"type\":[\"character\"]}",
			"rdt:type": "File",
			"rdt:scope": "undefined",
			"rdt:fromEnv": false,
			"rdt:hash": "440e703ad10b55ca5e2028dc071857c3",
			"rdt:timestamp": "2020-10-01T16.12.06-03",
			"rdt:location": "/home/mondelli/R/x86_64-pc-linux-gnu-library/4.0/tidyr/Meta/package.rds"
		},
		"rdt:d57": {
			"rdt:name": "package.rds",
			"rdt:value": "data/57-package.rds",
			"rdt:valType": "{\"container\":\"vector\", \"dimension\":[1], \"type\":[\"character\"]}",
			"rdt:type": "File",
			"rdt:scope": "undefined",
			"rdt:fromEnv": false,
			"rdt:hash": "f84a7483ef10680e790804a8f30e4eb3",
			"rdt:timestamp": "2020-07-06T20.07.46-03",
			"rdt:location": "/home/mondelli/R/x86_64-pc-linux-gnu-library/4.0/purrr/Meta/package.rds"
		},
		"rdt:d58": {
			"rdt:name": "package.rds",
			"rdt:value": "data/58-package.rds",
			"rdt:valType": "{\"container\":\"vector\", \"dimension\":[1], \"type\":[\"character\"]}",
			"rdt:type": "File",
			"rdt:scope": "undefined",
			"rdt:fromEnv": false,
			"rdt:hash": "cd32e57a297d4122cb3c09f2c52af20f",
			"rdt:timestamp": "2020-11-11T13.53.32-03",
			"rdt:location": "/home/mondelli/R/x86_64-pc-linux-gnu-library/4.0/readr/Meta/package.rds"
		},
		"rdt:d59": {
			"rdt:name": "package.rds",
			"rdt:value": "data/59-package.rds",
			"rdt:valType": "{\"container\":\"vector\", \"dimension\":[1], \"type\":[\"character\"]}",
			"rdt:type": "File",
			"rdt:scope": "undefined",
			"rdt:fromEnv": false,
			"rdt:hash": "1487fa93359739323344d6ebb3b5d9c2",
			"rdt:timestamp": "2020-07-06T20.19.16-03",
			"rdt:location": "/home/mondelli/R/x86_64-pc-linux-gnu-library/4.0/ggplot2/Meta/package.rds"
		},
		"rdt:d60": {
			"rdt:name": "package.rds",
			"rdt:value": "data/60-package.rds",
			"rdt:valType": "{\"container\":\"vector\", \"dimension\":[1], \"type\":[\"character\"]}",
			"rdt:type": "File",
			"rdt:scope": "undefined",
			"rdt:fromEnv": false,
			"rdt:hash": "36010952303b91fc9eba368839ea85dc",
			"rdt:timestamp": "2020-11-24T17.45.32-03",
			"rdt:location": "/home/mondelli/R/x86_64-pc-linux-gnu-library/4.0/magrittr/Meta/package.rds"
		},
		"rdt:d61": {
			"rdt:name": "package.rds",
			"rdt:value": "data/61-package.rds",
			"rdt:valType": "{\"container\":\"vector\", \"dimension\":[1], \"type\":[\"character\"]}",
			"rdt:type": "File",
			"rdt:scope": "undefined",
			"rdt:fromEnv": false,
			"rdt:hash": "4c758987849895182617bde10911c8e8",
			"rdt:timestamp": "2020-11-03T17.05.52-03",
			"rdt:location": "/home/mondelli/R/x86_64-pc-linux-gnu-library/4.0/rbibutils/Meta/package.rds"
		},
		"rdt:d62": {
			"rdt:name": "package.rds",
			"rdt:value": "data/62-package.rds",
			"rdt:valType": "{\"container\":\"vector\", \"dimension\":[1], \"type\":[\"character\"]}",
			"rdt:type": "File",
			"rdt:scope": "undefined",
			"rdt:fromEnv": false,
			"rdt:hash": "e42e20d0c9c7aaa8c35d58fa015cde01",
			"rdt:timestamp": "2020-05-16T12.30.19-03",
			"rdt:location": "/usr/lib/R/library/codetools/Meta/package.rds"
		},
		"rdt:d63": {
			"rdt:name": "package.rds",
			"rdt:value": "data/63-package.rds",
			"rdt:valType": "{\"container\":\"vector\", \"dimension\":[1], \"type\":[\"character\"]}",
			"rdt:type": "File",
			"rdt:scope": "undefined",
			"rdt:fromEnv": false,
			"rdt:hash": "69fa9344ae2c2507967136f6df3e4cf1",
			"rdt:timestamp": "2020-07-06T20.13.07-03",
			"rdt:location": "/home/mondelli/R/x86_64-pc-linux-gnu-library/4.0/scales/Meta/package.rds"
		},
		"rdt:d64": {
			"rdt:name": "package.rds",
			"rdt:value": "data/64-package.rds",
			"rdt:valType": "{\"container\":\"vector\", \"dimension\":[1], \"type\":[\"character\"]}",
			"rdt:type": "File",
			"rdt:scope": "undefined",
			"rdt:fromEnv": false,
			"rdt:hash": "59c341cf9ec13cd9df3565cc6fe61fe9",
			"rdt:timestamp": "2020-07-06T20.08.05-03",
			"rdt:location": "/home/mondelli/R/x86_64-pc-linux-gnu-library/4.0/ellipsis/Meta/package.rds"
		},
		"rdt:d65": {
			"rdt:name": "package.rds",
			"rdt:value": "data/65-package.rds",
			"rdt:valType": "{\"container\":\"vector\", \"dimension\":[1], \"type\":[\"character\"]}",
			"rdt:type": "File",
			"rdt:scope": "undefined",
			"rdt:fromEnv": false,
			"rdt:hash": "02acc4ff9c5f82d6fe497a1da7cb1682",
			"rdt:timestamp": "2020-07-06T19.59.45-03",
			"rdt:location": "/home/mondelli/R/x86_64-pc-linux-gnu-library/4.0/assertthat/Meta/package.rds"
		},
		"rdt:d66": {
			"rdt:name": "package.rds",
			"rdt:value": "data/66-package.rds",
			"rdt:valType": "{\"container\":\"vector\", \"dimension\":[1], \"type\":[\"character\"]}",
			"rdt:type": "File",
			"rdt:scope": "undefined",
			"rdt:fromEnv": false,
			"rdt:hash": "32f504251926a9367a626eb160ebf83d",
			"rdt:timestamp": "2020-10-01T17.10.33-03",
			"rdt:location": "/home/mondelli/R/x86_64-pc-linux-gnu-library/4.0/rdt/Meta/package.rds"
		},
		"rdt:d67": {
			"rdt:name": "package.rds",
			"rdt:value": "data/67-package.rds",
			"rdt:valType": "{\"container\":\"vector\", \"dimension\":[1], \"type\":[\"character\"]}",
			"rdt:type": "File",
			"rdt:scope": "undefined",
			"rdt:fromEnv": false,
			"rdt:hash": "6883f3c06cabbc80285bb59ef7b9d87c",
			"rdt:timestamp": "2020-11-24T17.45.42-03",
			"rdt:location": "/home/mondelli/R/x86_64-pc-linux-gnu-library/4.0/colorspace/Meta/package.rds"
		},
		"rdt:d68": {
			"rdt:name": "package.rds",
			"rdt:value": "data/68-package.rds",
			"rdt:valType": "{\"container\":\"vector\", \"dimension\":[1], \"type\":[\"character\"]}",
			"rdt:type": "File",
			"rdt:scope": "undefined",
			"rdt:fromEnv": false,
			"rdt:hash": "ba704e07deeceda2cac7074d7482fae7",
			"rdt:timestamp": "2020-11-11T13.48.10-03",
			"rdt:location": "/home/mondelli/R/x86_64-pc-linux-gnu-library/4.0/V8/Meta/package.rds"
		},
		"rdt:d69": {
			"rdt:name": "package.rds",
			"rdt:value": "data/69-package.rds",
			"rdt:valType": "{\"container\":\"vector\", \"dimension\":[1], \"type\":[\"character\"]}",
			"rdt:type": "File",
			"rdt:scope": "undefined",
			"rdt:fromEnv": false,
			"rdt:hash": "11a8b1916712d81cc5c29e045f8e9e68",
			"rdt:timestamp": "2020-10-01T16.01.34-03",
			"rdt:location": "/home/mondelli/R/x86_64-pc-linux-gnu-library/4.0/stringi/Meta/package.rds"
		},
		"rdt:d70": {
			"rdt:name": "package.rds",
			"rdt:value": "data/70-package.rds",
			"rdt:valType": "{\"container\":\"vector\", \"dimension\":[1], \"type\":[\"character\"]}",
			"rdt:type": "File",
			"rdt:scope": "undefined",
			"rdt:fromEnv": false,
			"rdt:hash": "124155dcb14b1b84d49589949a5ee9a9",
			"rdt:timestamp": "2020-07-06T20.07.57-03",
			"rdt:location": "/home/mondelli/R/x86_64-pc-linux-gnu-library/4.0/munsell/Meta/package.rds"
		},
		"rdt:d71": {
			"rdt:name": "package.rds",
			"rdt:value": "data/71-package.rds",
			"rdt:valType": "{\"container\":\"vector\", \"dimension\":[1], \"type\":[\"character\"]}",
			"rdt:type": "File",
			"rdt:scope": "undefined",
			"rdt:fromEnv": false,
			"rdt:hash": "38f948fdefacccff8358b6b9d05a5df0",
			"rdt:timestamp": "2020-07-06T19.59.34-03",
			"rdt:location": "/home/mondelli/R/x86_64-pc-linux-gnu-library/4.0/crayon/Meta/package.rds"
		},
		"rdt:d72": {
			"rdt:name": "package.rds",
			"rdt:value": "data/72-package.rds",
			"rdt:valType": "{\"container\":\"vector\", \"dimension\":[1], \"type\":[\"character\"]}",
			"rdt:type": "File",
			"rdt:scope": "undefined",
			"rdt:fromEnv": false,
			"rdt:hash": "f289ab9349ec62e2f280d1d87a8e7615",
			"rdt:timestamp": "2020-04-03T14.43.20-03",
			"rdt:location": "/usr/lib/R/library/lattice/Meta/package.rds"
		},
		"rdt:d73": {
			"rdt:name": "package.rds",
			"rdt:value": "data/73-package.rds",
			"rdt:valType": "{\"container\":\"vector\", \"dimension\":[1], \"type\":[\"character\"]}",
			"rdt:type": "File",
			"rdt:scope": "undefined",
			"rdt:fromEnv": false,
			"rdt:hash": "095345a9aa2dda0fa12e8d77034740ae",
			"rdt:timestamp": "2020-11-03T17.11.43-03",
			"rdt:location": "/home/mondelli/R/x86_64-pc-linux-gnu-library/4.0/rgdal/Meta/package.rds"
		},
		"rdt:d74": {
			"rdt:name": "sdmdata_1sp",
			"rdt:value": "data/74-sdmdata_1sp.csv",
			"rdt:valType": "{\"container\":\"data_frame\", \"dimension\":[604,9], \"type\":[\"integer\",\"numeric\",\"numeric\",\"numeric\",\"numeric\",\"numeric\",\"numeric\",\"numeric\",\"numeric\"]}",
			"rdt:type": "Snapshot",
			"rdt:scope": "R_GlobalEnv",
			"rdt:fromEnv": false,
			"rdt:hash": "",
			"rdt:timestamp": "2021-01-12T13.31.39-03",
			"rdt:location": ""
		},
		"rdt:d75": {
			"rdt:name": "sessionInfo.txt",
			"rdt:value": "data/75-sessionInfo.txt",
			"rdt:valType": "{\"container\":\"vector\", \"dimension\":[1], \"type\":[\"character\"]}",
			"rdt:type": "File",
			"rdt:scope": "undefined",
			"rdt:fromEnv": false,
			"rdt:hash": "317801e682c71bde05c7b21637956460",
			"rdt:timestamp": "2021-01-12T13.31.33-03",
			"rdt:location": "/home/mondelli/Dropbox/Reproducibility/prov2repr/prov_samples/modler_results/Abarema_langsdorffii/present/data_setup/sessionInfo.txt"
		},
		"rdt:d76": {
			"rdt:name": "metadata.csv",
			"rdt:value": "data/76-metadata.csv",
			"rdt:valType": "{\"container\":\"vector\", \"dimension\":[1], \"type\":[\"character\"]}",
			"rdt:type": "File",
			"rdt:scope": "undefined",
			"rdt:fromEnv": false,
			"rdt:hash": "9388890e1645f8d6f483c41fe1e56d71",
			"rdt:timestamp": "2021-01-12T13.31.38-03",
			"rdt:location": "/home/mondelli/Dropbox/Reproducibility/prov2repr/prov_samples/modler_results/Abarema_langsdorffii/present/data_setup/metadata.csv"
		},
		"rdt:d77": {
			"rdt:name": "sdmdata.csv",
			"rdt:value": "data/77-sdmdata.csv",
			"rdt:valType": "{\"container\":\"vector\", \"dimension\":[1], \"type\":[\"character\"]}",
			"rdt:type": "File",
			"rdt:scope": "undefined",
			"rdt:fromEnv": false,
			"rdt:hash": "5a0965ed981de30d31bccc419eff0f64",
			"rdt:timestamp": "2021-01-12T13.31.38-03",
			"rdt:location": "/home/mondelli/Dropbox/Reproducibility/prov2repr/prov_samples/modler_results/Abarema_langsdorffii/present/data_setup/sdmdata.csv"
		},
		"rdt:d78": {
			"rdt:name": "package.rds",
			"rdt:value": "data/78-package.rds",
			"rdt:valType": "{\"container\":\"vector\", \"dimension\":[1], \"type\":[\"character\"]}",
			"rdt:type": "File",
			"rdt:scope": "undefined",
			"rdt:fromEnv": false,
			"rdt:hash": "9ca941aca11675d29735facbdf02e964",
			"rdt:timestamp": "2020-06-23T09.11.46-03",
			"rdt:location": "/usr/lib/R/library/splines/Meta/package.rds"
		},
		"rdt:d79": {
			"rdt:name": "package.rds",
			"rdt:value": "data/79-package.rds",
			"rdt:valType": "{\"container\":\"vector\", \"dimension\":[1], \"type\":[\"character\"]}",
			"rdt:type": "File",
			"rdt:scope": "undefined",
			"rdt:fromEnv": false,
			"rdt:hash": "064d19347ee974909f5ef3df54a8c590",
			"rdt:timestamp": "2020-11-03T17.06.14-03",
			"rdt:location": "/home/mondelli/R/x86_64-pc-linux-gnu-library/4.0/foreach/Meta/package.rds"
		},
		"rdt:d80": {
			"rdt:name": "package.rds",
			"rdt:value": "data/80-package.rds",
			"rdt:valType": "{\"container\":\"vector\", \"dimension\":[1], \"type\":[\"character\"]}",
			"rdt:type": "File",
			"rdt:scope": "undefined",
			"rdt:fromEnv": false,
			"rdt:hash": "ad43e73fd852cdf5defb224c309528ec",
			"rdt:timestamp": "2020-07-06T20.16.08-03",
			"rdt:location": "/home/mondelli/R/x86_64-pc-linux-gnu-library/4.0/prodlim/Meta/package.rds"
		},
		"rdt:d81": {
			"rdt:name": "package.rds",
			"rdt:value": "data/81-package.rds",
			"rdt:valType": "{\"container\":\"vector\", \"dimension\":[1], \"type\":[\"character\"]}",
			"rdt:type": "File",
			"rdt:scope": "undefined",
			"rdt:fromEnv": false,
			"rdt:hash": "4611918f2d5655dfd1d67f2afc4050ec",
			"rdt:timestamp": "2020-06-23T09.11.46-03",
			"rdt:location": "/usr/lib/R/library/stats4/Meta/package.rds"
		},
		"rdt:d82": {
			"rdt:name": "package.rds",
			"rdt:value": "data/82-package.rds",
			"rdt:valType": "{\"container\":\"vector\", \"dimension\":[1], \"type\":[\"character\"]}",
			"rdt:type": "File",
			"rdt:scope": "undefined",
			"rdt:fromEnv": false,
			"rdt:hash": "7fb5a231ad635d74b1f8b4605e23765f",
			"rdt:timestamp": "2020-07-06T20.16.36-03",
			"rdt:location": "/home/mondelli/R/x86_64-pc-linux-gnu-library/4.0/ipred/Meta/package.rds"
		},
		"rdt:d83": {
			"rdt:name": "package.rds",
			"rdt:value": "data/83-package.rds",
			"rdt:valType": "{\"container\":\"vector\", \"dimension\":[1], \"type\":[\"character\"]}",
			"rdt:type": "File",
			"rdt:scope": "undefined",
			"rdt:fromEnv": false,
			"rdt:hash": "8f1b0a46dab8f66476feb3772dd25b4b",
			"rdt:timestamp": "2020-11-03T17.04.42-03",
			"rdt:location": "/home/mondelli/R/x86_64-pc-linux-gnu-library/4.0/digest/Meta/package.rds"
		},
		"rdt:d84": {
			"rdt:name": "package.rds",
			"rdt:value": "data/84-package.rds",
			"rdt:valType": "{\"container\":\"vector\", \"dimension\":[1], \"type\":[\"character\"]}",
			"rdt:type": "File",
			"rdt:scope": "undefined",
			"rdt:fromEnv": false,
			"rdt:hash": "04117ad74661a139ab0113d9a492502c",
			"rdt:timestamp": "2020-07-06T20.15.02-03",
			"rdt:location": "/home/mondelli/R/x86_64-pc-linux-gnu-library/4.0/pROC/Meta/package.rds"
		},
		"rdt:d85": {
			"rdt:name": "package.rds",
			"rdt:value": "data/85-package.rds",
			"rdt:valType": "{\"container\":\"vector\", \"dimension\":[1], \"type\":[\"character\"]}",
			"rdt:type": "File",
			"rdt:scope": "undefined",
			"rdt:fromEnv": false,
			"rdt:hash": "bb2e2c60c8ef4f97fcf74fc29964ac11",
			"rdt:timestamp": "2020-11-03T17.11.21-03",
			"rdt:location": "/home/mondelli/R/x86_64-pc-linux-gnu-library/4.0/recipes/Meta/package.rds"
		},
		"rdt:d86": {
			"rdt:name": "package.rds",
			"rdt:value": "data/86-package.rds",
			"rdt:valType": "{\"container\":\"vector\", \"dimension\":[1], \"type\":[\"character\"]}",
			"rdt:type": "File",
			"rdt:scope": "undefined",
			"rdt:fromEnv": false,
			"rdt:hash": "7d3773862b0710d98ca67b65b0c074e7",
			"rdt:timestamp": "2020-04-03T14.43.25-03",
			"rdt:location": "/usr/lib/R/library/Matrix/Meta/package.rds"
		},
		"rdt:d87": {
			"rdt:name": "package.rds",
			"rdt:value": "data/87-package.rds",
			"rdt:valType": "{\"container\":\"vector\", \"dimension\":[1], \"type\":[\"character\"]}",
			"rdt:type": "File",
			"rdt:scope": "undefined",
			"rdt:fromEnv": false,
			"rdt:hash": "cd6729eadf458080962e183056687560",
			"rdt:timestamp": "2020-07-06T20.00.20-03",
			"rdt:location": "/home/mondelli/R/x86_64-pc-linux-gnu-library/4.0/plyr/Meta/package.rds"
		},
		"rdt:d88": {
			"rdt:name": "package.rds",
			"rdt:value": "data/88-package.rds",
			"rdt:valType": "{\"container\":\"vector\", \"dimension\":[1], \"type\":[\"character\"]}",
			"rdt:type": "File",
			"rdt:scope": "undefined",
			"rdt:fromEnv": false,
			"rdt:hash": "9012a2b34f670e5c727996416c5669df",
			"rdt:timestamp": "2020-07-06T20.01.50-03",
			"rdt:location": "/home/mondelli/R/x86_64-pc-linux-gnu-library/4.0/timeDate/Meta/package.rds"
		},
		"rdt:d89": {
			"rdt:name": "package.rds",
			"rdt:value": "data/89-package.rds",
			"rdt:valType": "{\"container\":\"vector\", \"dimension\":[1], \"type\":[\"character\"]}",
			"rdt:type": "File",
			"rdt:scope": "undefined",
			"rdt:fromEnv": false,
			"rdt:hash": "6c7fc35a7514a30059e12bb15f3e0925",
			"rdt:timestamp": "2020-07-06T20.19.35-03",
			"rdt:location": "/home/mondelli/R/x86_64-pc-linux-gnu-library/4.0/caret/Meta/package.rds"
		},
		"rdt:d90": {
			"rdt:name": "package.rds",
			"rdt:value": "data/90-package.rds",
			"rdt:valType": "{\"container\":\"vector\", \"dimension\":[1], \"type\":[\"character\"]}",
			"rdt:type": "File",
			"rdt:scope": "undefined",
			"rdt:fromEnv": false,
			"rdt:hash": "48e1b2d0767aedabe83f1661e5625a2b",
			"rdt:timestamp": "2020-07-06T20.01.47-03",
			"rdt:location": "/home/mondelli/R/x86_64-pc-linux-gnu-library/4.0/gower/Meta/package.rds"
		},
		"rdt:d91": {
			"rdt:name": "package.rds",
			"rdt:value": "data/91-package.rds",
			"rdt:valType": "{\"container\":\"vector\", \"dimension\":[1], \"type\":[\"character\"]}",
			"rdt:type": "File",
			"rdt:scope": "undefined",
			"rdt:fromEnv": false,
			"rdt:hash": "4c836e224825a64e3e1ef15b7082b686",
			"rdt:timestamp": "2020-10-01T16.04.34-03",
			"rdt:location": "/home/mondelli/R/x86_64-pc-linux-gnu-library/4.0/lava/Meta/package.rds"
		},
		"rdt:d92": {
			"rdt:name": "package.rds",
			"rdt:value": "data/92-package.rds",
			"rdt:valType": "{\"container\":\"vector\", \"dimension\":[1], \"type\":[\"character\"]}",
			"rdt:type": "File",
			"rdt:scope": "undefined",
			"rdt:fromEnv": false,
			"rdt:hash": "d13db27a36ec5be67f124575daddb74b",
			"rdt:timestamp": "2020-04-28T14.37.45-03",
			"rdt:location": "/usr/lib/R/library/nnet/Meta/package.rds"
		},
		"rdt:d93": {
			"rdt:name": "package.rds",
			"rdt:value": "data/93-package.rds",
			"rdt:valType": "{\"container\":\"vector\", \"dimension\":[1], \"type\":[\"character\"]}",
			"rdt:type": "File",
			"rdt:scope": "undefined",
			"rdt:fromEnv": false,
			"rdt:hash": "f5307eb367a5abd7e7b11cfd11b893db",
			"rdt:timestamp": "2020-10-01T16.02.31-03",
			"rdt:location": "/home/mondelli/R/x86_64-pc-linux-gnu-library/4.0/survival/Meta/package.rds"
		},
		"rdt:d94": {
			"rdt:name": "package.rds",
			"rdt:value": "data/94-package.rds",
			"rdt:valType": "{\"container\":\"vector\", \"dimension\":[1], \"type\":[\"character\"]}",
			"rdt:type": "File",
			"rdt:scope": "undefined",
			"rdt:fromEnv": false,
			"rdt:hash": "c503e501621071e2037bae1ec5a14487",
			"rdt:timestamp": "2020-08-25T12.49.57-03",
			"rdt:location": "/usr/lib/R/library/nlme/Meta/package.rds"
		},
		"rdt:d95": {
			"rdt:name": "package.rds",
			"rdt:value": "data/95-package.rds",
			"rdt:valType": "{\"container\":\"vector\", \"dimension\":[1], \"type\":[\"character\"]}",
			"rdt:type": "File",
			"rdt:scope": "undefined",
			"rdt:fromEnv": false,
			"rdt:hash": "fbce61bdf03caca9d719ed3690a1aa0e",
			"rdt:timestamp": "2020-09-12T10.23.38-03",
			"rdt:location": "/usr/lib/R/library/MASS/Meta/package.rds"
		},
		"rdt:d96": {
			"rdt:name": "package.rds",
			"rdt:value": "data/96-package.rds",
			"rdt:valType": "{\"container\":\"vector\", \"dimension\":[1], \"type\":[\"character\"]}",
			"rdt:type": "File",
			"rdt:scope": "undefined",
			"rdt:fromEnv": false,
			"rdt:hash": "f5643c2f4bdf04a83c3a6d738c29d440",
			"rdt:timestamp": "2020-04-28T14.37.37-03",
			"rdt:location": "/usr/lib/R/library/class/Meta/package.rds"
		},
		"rdt:d97": {
			"rdt:name": "package.rds",
			"rdt:value": "data/97-package.rds",
			"rdt:valType": "{\"container\":\"vector\", \"dimension\":[1], \"type\":[\"character\"]}",
			"rdt:type": "File",
			"rdt:scope": "undefined",
			"rdt:fromEnv": false,
			"rdt:hash": "d9c14d450117039e9dadf6c630f508b8",
			"rdt:timestamp": "2020-11-03T17.05.03-03",
			"rdt:location": "/home/mondelli/R/x86_64-pc-linux-gnu-library/4.0/data.table/Meta/package.rds"
		},
		"rdt:d98": {
			"rdt:name": "package.rds",
			"rdt:value": "data/98-package.rds",
			"rdt:valType": "{\"container\":\"vector\", \"dimension\":[1], \"type\":[\"character\"]}",
			"rdt:type": "File",
			"rdt:scope": "undefined",
			"rdt:fromEnv": false,
			"rdt:hash": "aa7d6507c31f8d9b0a0d8e949a34ff8b",
			"rdt:timestamp": "2020-11-03T17.04.23-03",
			"rdt:location": "/home/mondelli/R/x86_64-pc-linux-gnu-library/4.0/iterators/Meta/package.rds"
		},
		"rdt:d99": {
			"rdt:name": "package.rds",
			"rdt:value": "data/99-package.rds",
			"rdt:valType": "{\"container\":\"vector\", \"dimension\":[1], \"type\":[\"character\"]}",
			"rdt:type": "File",
			"rdt:scope": "undefined",
			"rdt:fromEnv": false,
			"rdt:hash": "0194adad613b16f55ed1729a6eea5457",
			"rdt:timestamp": "2020-07-06T20.14.29-03",
			"rdt:location": "/home/mondelli/R/x86_64-pc-linux-gnu-library/4.0/ModelMetrics/Meta/package.rds"
		},
		"rdt:d100": {
			"rdt:name": "package.rds",
			"rdt:value": "data/100-package.rds",
			"rdt:valType": "{\"container\":\"vector\", \"dimension\":[1], \"type\":[\"character\"]}",
			"rdt:type": "File",
			"rdt:scope": "undefined",
			"rdt:fromEnv": false,
			"rdt:hash": "4caae2bf7ed78994ed94cf6ef3292ad9",
			"rdt:timestamp": "2020-07-06T20.14.52-03",
			"rdt:location": "/home/mondelli/R/x86_64-pc-linux-gnu-library/4.0/reshape2/Meta/package.rds"
		},
		"rdt:d101": {
			"rdt:name": "package.rds",
			"rdt:value": "data/101-package.rds",
			"rdt:valType": "{\"container\":\"vector\", \"dimension\":[1], \"type\":[\"character\"]}",
			"rdt:type": "File",
			"rdt:scope": "undefined",
			"rdt:fromEnv": false,
			"rdt:hash": "c5d5a7aea3f6506f852d01511cb2a904",
			"rdt:timestamp": "2020-07-06T20.08.19-03",
			"rdt:location": "/home/mondelli/R/x86_64-pc-linux-gnu-library/4.0/lubridate/Meta/package.rds"
		},
		"rdt:d102": {
			"rdt:name": "package.rds",
			"rdt:value": "data/102-package.rds",
			"rdt:valType": "{\"container\":\"vector\", \"dimension\":[1], \"type\":[\"character\"]}",
			"rdt:type": "File",
			"rdt:scope": "undefined",
			"rdt:fromEnv": false,
			"rdt:hash": "44983abb16244dc4ae9503c95021fb0e",
			"rdt:timestamp": "2020-04-03T14.43.52-03",
			"rdt:location": "/usr/lib/R/library/rpart/Meta/package.rds"
		},
		"rdt:d103": {
			"rdt:name": "package.rds",
			"rdt:value": "data/103-package.rds",
			"rdt:valType": "{\"container\":\"vector\", \"dimension\":[1], \"type\":[\"character\"]}",
			"rdt:type": "File",
			"rdt:scope": "undefined",
			"rdt:fromEnv": false,
			"rdt:hash": "a413929d87cc6e7221b0daade898d49b",
			"rdt:timestamp": "2020-09-29T09.59.39-03",
			"rdt:location": "/usr/lib/R/library/survival/Meta/package.rds"
		},
		"rdt:d104": {
			"rdt:name": "many",
			"rdt:value": "data/104-many.csv",
			"rdt:valType": "{\"container\":\"data_frame\", \"dimension\":[1,33], \"type\":[\"numeric\",\"numeric\",\"numeric\",\"numeric\",\"numeric\",\"numeric\",\"character\",\"character\",\"integer\",\"integer\",\"integer\",\"integer\",\"numeric\",\"numeric\",\"numeric\",\"logical\",\"numeric\",\"numeric\",\"numeric\",\"numeric\",\"numeric\",\"character\",\"numeric\",\"numeric\",\"numeric\",\"numeric\",\"numeric\",\"numeric\",\"numeric\",\"numeric\",\"numeric\",\"numeric\",\"numeric\"]}",
			"rdt:type": "Snapshot",
			"rdt:scope": "R_GlobalEnv",
			"rdt:fromEnv": false,
			"rdt:hash": "",
			"rdt:timestamp": "2021-01-12T13.32.02-03",
			"rdt:location": ""
		},
		"rdt:d105": {
			"rdt:name": "sessionInfo.txt",
			"rdt:value": "data/105-sessionInfo.txt",
			"rdt:valType": "{\"container\":\"vector\", \"dimension\":[1], \"type\":[\"character\"]}",
			"rdt:type": "File",
			"rdt:scope": "undefined",
			"rdt:fromEnv": false,
			"rdt:hash": "1cb71905710e694b6d2c8037fbeff92a",
			"rdt:timestamp": "2021-01-12T13.31.42-03",
			"rdt:location": "/home/mondelli/Dropbox/Reproducibility/prov2repr/prov_samples/modler_results/Abarema_langsdorffii/present/partitions/sessionInfo.txt"
		},
		"rdt:d106": {
			"rdt:name": "eval_mod_Abarema_langsdorffii_1_3_brt.csv",
			"rdt:value": "data/106-eval_mod_Abarema_langsdorffii_1_3_brt.csv",
			"rdt:valType": "{\"container\":\"vector\", \"dimension\":[1], \"type\":[\"character\"]}",
			"rdt:type": "File",
			"rdt:scope": "undefined",
			"rdt:fromEnv": false,
			"rdt:hash": "32d2b37c064e5d7f9bdb669d9208dd47",
			"rdt:timestamp": "2021-01-12T13.31.47-03",
			"rdt:location": "/home/mondelli/Dropbox/Reproducibility/prov2repr/prov_samples/modler_results/Abarema_langsdorffii/present/partitions/eval_mod_Abarema_langsdorffii_1_3_brt.csv"
		},
		"rdt:d107": {
			"rdt:name": "evaluate_Abarema_langsdorffii_1_3_brt.csv",
			"rdt:value": "data/107-evaluate_Abarema_langsdorffii_1_3_brt.csv",
			"rdt:valType": "{\"container\":\"vector\", \"dimension\":[1], \"type\":[\"character\"]}",
			"rdt:type": "File",
			"rdt:scope": "undefined",
			"rdt:fromEnv": false,
			"rdt:hash": "84da295b5540d71a66aa2615df3f9739",
			"rdt:timestamp": "2021-01-12T13.31.47-03",
			"rdt:location": "/home/mondelli/Dropbox/Reproducibility/prov2repr/prov_samples/modler_results/Abarema_langsdorffii/present/partitions/evaluate_Abarema_langsdorffii_1_3_brt.csv"
		},
		"rdt:d108": {
			"rdt:name": "brt_model_Abarema_langsdorffii_1_3.rda",
			"rdt:value": "data/108-brt_model_Abarema_langsdorffii_1_3.rda",
			"rdt:valType": "{\"container\":\"vector\", \"dimension\":[1], \"type\":[\"character\"]}",
			"rdt:type": "File",
			"rdt:scope": "undefined",
			"rdt:fromEnv": false,
			"rdt:hash": "a6c9bf6a3094bbbb70c373c4106df379",
			"rdt:timestamp": "2021-01-12T13.31.48-03",
			"rdt:location": "/home/mondelli/Dropbox/Reproducibility/prov2repr/prov_samples/modler_results/Abarema_langsdorffii/present/partitions/brt_model_Abarema_langsdorffii_1_3.rda"
		},
		"rdt:d109": {
			"rdt:name": "eval_mod_Abarema_langsdorffii_1_2_brt.csv",
			"rdt:value": "data/109-eval_mod_Abarema_langsdorffii_1_2_brt.csv",
			"rdt:valType": "{\"container\":\"vector\", \"dimension\":[1], \"type\":[\"character\"]}",
			"rdt:type": "File",
			"rdt:scope": "undefined",
			"rdt:fromEnv": false,
			"rdt:hash": "e4888d6f8e8a5e1af5d7c89002317d6f",
			"rdt:timestamp": "2021-01-12T13.31.51-03",
			"rdt:location": "/home/mondelli/Dropbox/Reproducibility/prov2repr/prov_samples/modler_results/Abarema_langsdorffii/present/partitions/eval_mod_Abarema_langsdorffii_1_2_brt.csv"
		},
		"rdt:d110": {
			"rdt:name": "evaluate_Abarema_langsdorffii_1_2_brt.csv",
			"rdt:value": "data/110-evaluate_Abarema_langsdorffii_1_2_brt.csv",
			"rdt:valType": "{\"container\":\"vector\", \"dimension\":[1], \"type\":[\"character\"]}",
			"rdt:type": "File",
			"rdt:scope": "undefined",
			"rdt:fromEnv": false,
			"rdt:hash": "d8c3a7df395dd0952abf2b2a03606f85",
			"rdt:timestamp": "2021-01-12T13.31.51-03",
			"rdt:location": "/home/mondelli/Dropbox/Reproducibility/prov2repr/prov_samples/modler_results/Abarema_langsdorffii/present/partitions/evaluate_Abarema_langsdorffii_1_2_brt.csv"
		},
		"rdt:d111": {
			"rdt:name": "brt_model_Abarema_langsdorffii_1_2.rda",
			"rdt:value": "data/111-brt_model_Abarema_langsdorffii_1_2.rda",
			"rdt:valType": "{\"container\":\"vector\", \"dimension\":[1], \"type\":[\"character\"]}",
			"rdt:type": "File",
			"rdt:scope": "undefined",
			"rdt:fromEnv": false,
			"rdt:hash": "e848b06e305a490bd6a97628727dcac9",
			"rdt:timestamp": "2021-01-12T13.31.51-03",
			"rdt:location": "/home/mondelli/Dropbox/Reproducibility/prov2repr/prov_samples/modler_results/Abarema_langsdorffii/present/partitions/brt_model_Abarema_langsdorffii_1_2.rda"
		},
		"rdt:d112": {
			"rdt:name": "eval_mod_Abarema_langsdorffii_1_1_brt.csv",
			"rdt:value": "data/112-eval_mod_Abarema_langsdorffii_1_1_brt.csv",
			"rdt:valType": "{\"container\":\"vector\", \"dimension\":[1], \"type\":[\"character\"]}",
			"rdt:type": "File",
			"rdt:scope": "undefined",
			"rdt:fromEnv": false,
			"rdt:hash": "250e214497787d4e714815cd6cf8f666",
			"rdt:timestamp": "2021-01-12T13.31.54-03",
			"rdt:location": "/home/mondelli/Dropbox/Reproducibility/prov2repr/prov_samples/modler_results/Abarema_langsdorffii/present/partitions/eval_mod_Abarema_langsdorffii_1_1_brt.csv"
		},
		"rdt:d113": {
			"rdt:name": "evaluate_Abarema_langsdorffii_1_1_brt.csv",
			"rdt:value": "data/113-evaluate_Abarema_langsdorffii_1_1_brt.csv",
			"rdt:valType": "{\"container\":\"vector\", \"dimension\":[1], \"type\":[\"character\"]}",
			"rdt:type": "File",
			"rdt:scope": "undefined",
			"rdt:fromEnv": false,
			"rdt:hash": "96b45405a97380e4844d420a2311a13b",
			"rdt:timestamp": "2021-01-12T13.31.54-03",
			"rdt:location": "/home/mondelli/Dropbox/Reproducibility/prov2repr/prov_samples/modler_results/Abarema_langsdorffii/present/partitions/evaluate_Abarema_langsdorffii_1_1_brt.csv"
		},
		"rdt:d114": {
			"rdt:name": "brt_model_Abarema_langsdorffii_1_1.rda",
			"rdt:value": "data/114-brt_model_Abarema_langsdorffii_1_1.rda",
			"rdt:valType": "{\"container\":\"vector\", \"dimension\":[1], \"type\":[\"character\"]}",
			"rdt:type": "File",
			"rdt:scope": "undefined",
			"rdt:fromEnv": false,
			"rdt:hash": "bc1a1d15297f5d8cc3a215ce25412e01",
			"rdt:timestamp": "2021-01-12T13.31.55-03",
			"rdt:location": "/home/mondelli/Dropbox/Reproducibility/prov2repr/prov_samples/modler_results/Abarema_langsdorffii/present/partitions/brt_model_Abarema_langsdorffii_1_1.rda"
		},
		"rdt:d115": {
			"rdt:name": "eval_mod_Abarema_langsdorffii_1_4_brt.csv",
			"rdt:value": "data/115-eval_mod_Abarema_langsdorffii_1_4_brt.csv",
			"rdt:valType": "{\"container\":\"vector\", \"dimension\":[1], \"type\":[\"character\"]}",
			"rdt:type": "File",
			"rdt:scope": "undefined",
			"rdt:fromEnv": false,
			"rdt:hash": "3f0b174b9261ee271f1a0deb041b7421",
			"rdt:timestamp": "2021-01-12T13.31.58-03",
			"rdt:location": "/home/mondelli/Dropbox/Reproducibility/prov2repr/prov_samples/modler_results/Abarema_langsdorffii/present/partitions/eval_mod_Abarema_langsdorffii_1_4_brt.csv"
		},
		"rdt:d116": {
			"rdt:name": "evaluate_Abarema_langsdorffii_1_4_brt.csv",
			"rdt:value": "data/116-evaluate_Abarema_langsdorffii_1_4_brt.csv",
			"rdt:valType": "{\"container\":\"vector\", \"dimension\":[1], \"type\":[\"character\"]}",
			"rdt:type": "File",
			"rdt:scope": "undefined",
			"rdt:fromEnv": false,
			"rdt:hash": "252367bb4435d6628a7c304af235abf4",
			"rdt:timestamp": "2021-01-12T13.31.58-03",
			"rdt:location": "/home/mondelli/Dropbox/Reproducibility/prov2repr/prov_samples/modler_results/Abarema_langsdorffii/present/partitions/evaluate_Abarema_langsdorffii_1_4_brt.csv"
		},
		"rdt:d117": {
			"rdt:name": "brt_model_Abarema_langsdorffii_1_4.rda",
			"rdt:value": "data/117-brt_model_Abarema_langsdorffii_1_4.rda",
			"rdt:valType": "{\"container\":\"vector\", \"dimension\":[1], \"type\":[\"character\"]}",
			"rdt:type": "File",
			"rdt:scope": "undefined",
			"rdt:fromEnv": false,
			"rdt:hash": "c30fa5110c2bfeb427107d0cd928cec7",
			"rdt:timestamp": "2021-01-12T13.31.58-03",
			"rdt:location": "/home/mondelli/Dropbox/Reproducibility/prov2repr/prov_samples/modler_results/Abarema_langsdorffii/present/partitions/brt_model_Abarema_langsdorffii_1_4.rda"
		},
		"rdt:d118": {
			"rdt:name": "eval_mod_Abarema_langsdorffii_1_5_brt.csv",
			"rdt:value": "data/118-eval_mod_Abarema_langsdorffii_1_5_brt.csv",
			"rdt:valType": "{\"container\":\"vector\", \"dimension\":[1], \"type\":[\"character\"]}",
			"rdt:type": "File",
			"rdt:scope": "undefined",
			"rdt:fromEnv": false,
			"rdt:hash": "248d5213b1e24f88cda07414369037ab",
			"rdt:timestamp": "2021-01-12T13.32.02-03",
			"rdt:location": "/home/mondelli/Dropbox/Reproducibility/prov2repr/prov_samples/modler_results/Abarema_langsdorffii/present/partitions/eval_mod_Abarema_langsdorffii_1_5_brt.csv"
		},
		"rdt:d119": {
			"rdt:name": "evaluate_Abarema_langsdorffii_1_5_brt.csv",
			"rdt:value": "data/119-evaluate_Abarema_langsdorffii_1_5_brt.csv",
			"rdt:valType": "{\"container\":\"vector\", \"dimension\":[1], \"type\":[\"character\"]}",
			"rdt:type": "File",
			"rdt:scope": "undefined",
			"rdt:fromEnv": false,
			"rdt:hash": "3ac7033d286d9d5a8644a5ac287327bd",
			"rdt:timestamp": "2021-01-12T13.32.02-03",
			"rdt:location": "/home/mondelli/Dropbox/Reproducibility/prov2repr/prov_samples/modler_results/Abarema_langsdorffii/present/partitions/evaluate_Abarema_langsdorffii_1_5_brt.csv"
		},
		"rdt:d120": {
			"rdt:name": "brt_model_Abarema_langsdorffii_1_5.rda",
			"rdt:value": "data/120-brt_model_Abarema_langsdorffii_1_5.rda",
			"rdt:valType": "{\"container\":\"vector\", \"dimension\":[1], \"type\":[\"character\"]}",
			"rdt:type": "File",
			"rdt:scope": "undefined",
			"rdt:fromEnv": false,
			"rdt:hash": "2dd3ae0a40cfcb6dee9f6d7c91a688ef",
			"rdt:timestamp": "2021-01-12T13.32.02-03",
			"rdt:location": "/home/mondelli/Dropbox/Reproducibility/prov2repr/prov_samples/modler_results/Abarema_langsdorffii/present/partitions/brt_model_Abarema_langsdorffii_1_5.rda"
		},
		"rdt:d121": {
			"rdt:name": "package.rds",
			"rdt:value": "data/121-package.rds",
			"rdt:valType": "{\"container\":\"vector\", \"dimension\":[1], \"type\":[\"character\"]}",
			"rdt:type": "File",
			"rdt:scope": "undefined",
			"rdt:fromEnv": false,
			"rdt:hash": "5b9682312676a72536b868dfb24d9909",
			"rdt:timestamp": "2020-10-01T16.04.06-03",
			"rdt:location": "/home/mondelli/R/x86_64-pc-linux-gnu-library/4.0/gbm/Meta/package.rds"
		},
		"rdt:d122": {
			"rdt:name": "fm",
			"rdt:value": "data/122-fm.csv",
			"rdt:valType": "{\"container\":\"data_frame\", \"dimension\":[5,33], \"type\":[\"numeric\",\"numeric\",\"numeric\",\"numeric\",\"numeric\",\"numeric\",\"character\",\"character\",\"integer\",\"integer\",\"integer\",\"integer\",\"numeric\",\"numeric\",\"numeric\",\"logical\",\"numeric\",\"numeric\",\"integer\",\"numeric\",\"numeric\",\"character\",\"numeric\",\"numeric\",\"numeric\",\"numeric\",\"numeric\",\"numeric\",\"numeric\",\"numeric\",\"numeric\",\"numeric\",\"numeric\"]}",
			"rdt:type": "Snapshot",
			"rdt:scope": "R_GlobalEnv",
			"rdt:fromEnv": false,
			"rdt:hash": "",
			"rdt:timestamp": "2021-01-12T13.32.16-03",
			"rdt:location": ""
		},
		"rdt:d123": {
			"rdt:name": "Abarema_langsdorffii_final_statistics.csv",
			"rdt:value": "data/123-Abarema_langsdorffii_final_statistics.csv",
			"rdt:valType": "{\"container\":\"vector\", \"dimension\":[1], \"type\":[\"character\"]}",
			"rdt:type": "File",
			"rdt:scope": "undefined",
			"rdt:fromEnv": false,
			"rdt:hash": "474e46fb9417d8d8554ae46b7f340d5c",
			"rdt:timestamp": "2021-01-12T13.32.07-03",
			"rdt:location": "/home/mondelli/Dropbox/Reproducibility/prov2repr/prov_samples/modler_results/Abarema_langsdorffii/present/final_models/Abarema_langsdorffii_final_statistics.csv"
		},
		"rdt:d124": {
			"rdt:name": "Abarema_langsdorffii_mean_statistics.csv",
			"rdt:value": "data/124-Abarema_langsdorffii_mean_statistics.csv",
			"rdt:valType": "{\"container\":\"vector\", \"dimension\":[1], \"type\":[\"character\"]}",
			"rdt:type": "File",
			"rdt:scope": "undefined",
			"rdt:fromEnv": false,
			"rdt:hash": "1c6e5ac9f3e1d9045ee1e3ba472c72ee",
			"rdt:timestamp": "2021-01-12T13.32.07-03",
			"rdt:location": "/home/mondelli/Dropbox/Reproducibility/prov2repr/prov_samples/modler_results/Abarema_langsdorffii/present/final_models/Abarema_langsdorffii_mean_statistics.csv"
		},
		"rdt:d125": {
			"rdt:name": "metadata.csv",
			"rdt:value": "data/125-metadata.csv",
			"rdt:valType": "{\"container\":\"vector\", \"dimension\":[1], \"type\":[\"character\"]}",
			"rdt:type": "File",
			"rdt:scope": "undefined",
			"rdt:fromEnv": false,
			"rdt:hash": "aca718a4a7c8a14ba7489b7617e16158",
			"rdt:timestamp": "2021-01-12T13.32.16-03",
			"rdt:location": "/home/mondelli/Dropbox/Reproducibility/prov2repr/prov_samples/modler_results/Abarema_langsdorffii/present/final_models/metadata.csv"
		},
		"rdt:d126": {
			"rdt:name": "sessionInfo.txt",
			"rdt:value": "data/126-sessionInfo.txt",
			"rdt:valType": "{\"container\":\"vector\", \"dimension\":[1], \"type\":[\"character\"]}",
			"rdt:type": "File",
			"rdt:scope": "undefined",
			"rdt:fromEnv": false,
			"rdt:hash": "75eb5c070990d63d049a0cd9e66191ed",
			"rdt:timestamp": "2021-01-12T13.32.16-03",
			"rdt:location": "/home/mondelli/Dropbox/Reproducibility/prov2repr/prov_samples/modler_results/Abarema_langsdorffii/present/final_models/sessionInfo.txt"
		},
		"rdt:d127": {
			"rdt:name": "ens",
			"rdt:value": "data/127-ens.txt",
			"rdt:valType": "RasterStack",
			"rdt:type": "Snapshot",
			"rdt:scope": "R_GlobalEnv",
			"rdt:fromEnv": false,
			"rdt:hash": "",
			"rdt:timestamp": "2021-01-12T13.32.26-03",
			"rdt:location": ""
		},
		"rdt:d128": {
			"rdt:name": "metadata.csv",
			"rdt:value": "data/128-metadata.csv",
			"rdt:valType": "{\"container\":\"vector\", \"dimension\":[1], \"type\":[\"character\"]}",
			"rdt:type": "File",
			"rdt:scope": "undefined",
			"rdt:fromEnv": false,
			"rdt:hash": "9bce507a89fb196e9eda17857d6135d0",
			"rdt:timestamp": "2021-01-12T13.32.25-03",
			"rdt:location": "/home/mondelli/Dropbox/Reproducibility/prov2repr/prov_samples/modler_results/Abarema_langsdorffii/present/ensemble/metadata.csv"
		},
		"rdt:d129": {
			"rdt:name": "sessionInfo.txt",
			"rdt:value": "data/129-sessionInfo.txt",
			"rdt:valType": "{\"container\":\"vector\", \"dimension\":[1], \"type\":[\"character\"]}",
			"rdt:type": "File",
			"rdt:scope": "undefined",
			"rdt:fromEnv": false,
			"rdt:hash": "75eb5c070990d63d049a0cd9e66191ed",
			"rdt:timestamp": "2021-01-12T13.32.26-03",
			"rdt:location": "/home/mondelli/Dropbox/Reproducibility/prov2repr/prov_samples/modler_results/Abarema_langsdorffii/present/ensemble/sessionInfo.txt"
		},

		"rdt:environment": {
			"rdt:name": "environment",
			"rdt:architecture": "x86_64-pc-linux-gnu (64-bit)",
			"rdt:operatingSystem": "Ubuntu 20.04.1 LTS",
			"rdt:language": "R",
			"rdt:langVersion": "R version 4.0.2 (2020-06-22)",
			"rdt:script": "/home/mondelli/Dropbox/Reproducibility/prov2repr/util/prov_samples/prov_console_2021-01-12T13.31.09-03/scripts/console.R",
			"rdt:scriptTimeStamp": "2021-01-12T13.31.09-03",
			"rdt:scriptHash": "",
			"rdt:totalElapsedTime": "51.991",
			"rdt:sourcedScripts": "",
			"rdt:sourcedScriptTimeStamps": "",
			"rdt:sourcedScriptHashes": "",
			"rdt:workingDirectory": "/home/mondelli",
			"rdt:provDirectory": "/home/mondelli/Dropbox/Reproducibility/prov2repr/util/prov_samples/prov_console_2021-01-12T13.31.09-03",
			"rdt:provTimestamp": "2021-01-12T13.31.09-03",
			"rdt:hashAlgorithm": "md5"
		},

		"rdt:l1": {
			"name": "base",
			"version": "4.0.2",
			"prov:type": {
				"$": "prov:Collection",
				"type": "xsd:QName"
			}
		},
		"rdt:l2": {
			"name": "datasets",
			"version": "4.0.2",
			"prov:type": {
				"$": "prov:Collection",
				"type": "xsd:QName"
			}
		},
		"rdt:l3": {
			"name": "dplyr",
			"version": "1.0.2",
			"prov:type": {
				"$": "prov:Collection",
				"type": "xsd:QName"
			}
		},
		"rdt:l4": {
			"name": "ggplot2",
			"version": "3.3.2",
			"prov:type": {
				"$": "prov:Collection",
				"type": "xsd:QName"
			}
		},
		"rdt:l5": {
			"name": "graphics",
			"version": "4.0.2",
			"prov:type": {
				"$": "prov:Collection",
				"type": "xsd:QName"
			}
		},
		"rdt:l6": {
			"name": "grDevices",
			"version": "4.0.2",
			"prov:type": {
				"$": "prov:Collection",
				"type": "xsd:QName"
			}
		},
		"rdt:l7": {
			"name": "methods",
			"version": "4.0.2",
			"prov:type": {
				"$": "prov:Collection",
				"type": "xsd:QName"
			}
		},
		"rdt:l8": {
			"name": "modleR",
			"version": "0.0.1",
			"prov:type": {
				"$": "prov:Collection",
				"type": "xsd:QName"
			}
		},
		"rdt:l9": {
			"name": "sp",
			"version": "1.4-4",
			"prov:type": {
				"$": "prov:Collection",
				"type": "xsd:QName"
			}
		},
		"rdt:l10": {
			"name": "stats",
			"version": "4.0.2",
			"prov:type": {
				"$": "prov:Collection",
				"type": "xsd:QName"
			}
		},
		"rdt:l11": {
			"name": "utils",
			"version": "4.0.2",
			"prov:type": {
				"$": "prov:Collection",
				"type": "xsd:QName"
			}
		},

		"rdt:f1": {
			"name": "setup_sdmdata"
		},
		"rdt:f2": {
			"name": "do_many"
		},
		"rdt:f3": {
			"name": "final_model"
		},
		"rdt:f4": {
			"name": "ensemble_model"
		}
	},

	"wasInformedBy" : {
		"rdt:pp1": {
			"prov:informant": "rdt:p1",
			"prov:informed": "rdt:p2"
		},
		"rdt:pp2": {
			"prov:informant": "rdt:p2",
			"prov:informed": "rdt:p3"
		},
		"rdt:pp3": {
			"prov:informant": "rdt:p3",
			"prov:informed": "rdt:p4"
		},
		"rdt:pp4": {
			"prov:informant": "rdt:p4",
			"prov:informed": "rdt:p5"
		},
		"rdt:pp5": {
			"prov:informant": "rdt:p5",
			"prov:informed": "rdt:p6"
		},
		"rdt:pp6": {
			"prov:informant": "rdt:p6",
			"prov:informed": "rdt:p7"
		},
		"rdt:pp7": {
			"prov:informant": "rdt:p7",
			"prov:informed": "rdt:p8"
		},
		"rdt:pp8": {
			"prov:informant": "rdt:p8",
			"prov:informed": "rdt:p9"
		},
		"rdt:pp9": {
			"prov:informant": "rdt:p9",
			"prov:informed": "rdt:p10"
		},
		"rdt:pp10": {
			"prov:informant": "rdt:p10",
			"prov:informed": "rdt:p11"
		}
	},

	"wasGeneratedBy" : {
		"rdt:pd1": {
			"prov:activity": "rdt:p4",
			"prov:entity": "rdt:d1"
		},
		"rdt:pd2": {
			"prov:activity": "rdt:p5",
			"prov:entity": "rdt:d2"
		},
		"rdt:pd3": {
			"prov:activity": "rdt:p6",
			"prov:entity": "rdt:d3"
		},
		"rdt:pd4": {
			"prov:activity": "rdt:p7",
			"prov:entity": "rdt:d74"
		},
		"rdt:pd5": {
			"prov:activity": "rdt:p7",
			"prov:entity": "rdt:d75"
		},
		"rdt:pd6": {
			"prov:activity": "rdt:p7",
			"prov:entity": "rdt:d76"
		},
		"rdt:pd7": {
			"prov:activity": "rdt:p7",
			"prov:entity": "rdt:d77"
		},
		"rdt:pd8": {
			"prov:activity": "rdt:p8",
			"prov:entity": "rdt:d104"
		},
		"rdt:pd9": {
			"prov:activity": "rdt:p8",
			"prov:entity": "rdt:d105"
		},
		"rdt:pd10": {
			"prov:activity": "rdt:p8",
			"prov:entity": "rdt:d106"
		},
		"rdt:pd11": {
			"prov:activity": "rdt:p8",
			"prov:entity": "rdt:d107"
		},
		"rdt:pd12": {
			"prov:activity": "rdt:p8",
			"prov:entity": "rdt:d108"
		},
		"rdt:pd13": {
			"prov:activity": "rdt:p8",
			"prov:entity": "rdt:d109"
		},
		"rdt:pd14": {
			"prov:activity": "rdt:p8",
			"prov:entity": "rdt:d110"
		},
		"rdt:pd15": {
			"prov:activity": "rdt:p8",
			"prov:entity": "rdt:d111"
		},
		"rdt:pd16": {
			"prov:activity": "rdt:p8",
			"prov:entity": "rdt:d112"
		},
		"rdt:pd17": {
			"prov:activity": "rdt:p8",
			"prov:entity": "rdt:d113"
		},
		"rdt:pd18": {
			"prov:activity": "rdt:p8",
			"prov:entity": "rdt:d114"
		},
		"rdt:pd19": {
			"prov:activity": "rdt:p8",
			"prov:entity": "rdt:d115"
		},
		"rdt:pd20": {
			"prov:activity": "rdt:p8",
			"prov:entity": "rdt:d116"
		},
		"rdt:pd21": {
			"prov:activity": "rdt:p8",
			"prov:entity": "rdt:d117"
		},
		"rdt:pd22": {
			"prov:activity": "rdt:p8",
			"prov:entity": "rdt:d118"
		},
		"rdt:pd23": {
			"prov:activity": "rdt:p8",
			"prov:entity": "rdt:d119"
		},
		"rdt:pd24": {
			"prov:activity": "rdt:p8",
			"prov:entity": "rdt:d120"
		},
		"rdt:pd25": {
			"prov:activity": "rdt:p9",
			"prov:entity": "rdt:d122"
		},
		"rdt:pd26": {
			"prov:activity": "rdt:p9",
			"prov:entity": "rdt:d123"
		},
		"rdt:pd27": {
			"prov:activity": "rdt:p9",
			"prov:entity": "rdt:d124"
		},
		"rdt:pd28": {
			"prov:activity": "rdt:p9",
			"prov:entity": "rdt:d125"
		},
		"rdt:pd29": {
			"prov:activity": "rdt:p9",
			"prov:entity": "rdt:d126"
		},
		"rdt:pd30": {
			"prov:activity": "rdt:p10",
			"prov:entity": "rdt:d127"
		},
		"rdt:pd31": {
			"prov:activity": "rdt:p10",
			"prov:entity": "rdt:d128"
		},
		"rdt:pd32": {
			"prov:activity": "rdt:p10",
			"prov:entity": "rdt:d129"
		}
	},

	"used" : {
		"rdt:dp1": {
			"prov:entity": "rdt:d1",
			"prov:activity": "rdt:p7"
		},
		"rdt:dp2": {
			"prov:entity": "rdt:d2",
			"prov:activity": "rdt:p7"
		},
		"rdt:dp3": {
			"prov:entity": "rdt:d3",
			"prov:activity": "rdt:p7"
		},
		"rdt:dp4": {
			"prov:entity": "rdt:d4",
			"prov:activity": "rdt:p7"
		},
		"rdt:dp5": {
			"prov:entity": "rdt:d5",
			"prov:activity": "rdt:p7"
		},
		"rdt:dp6": {
			"prov:entity": "rdt:d6",
			"prov:activity": "rdt:p7"
		},
		"rdt:dp7": {
			"prov:entity": "rdt:d7",
			"prov:activity": "rdt:p7"
		},
		"rdt:dp8": {
			"prov:entity": "rdt:d8",
			"prov:activity": "rdt:p7"
		},
		"rdt:dp9": {
			"prov:entity": "rdt:d9",
			"prov:activity": "rdt:p7"
		},
		"rdt:dp10": {
			"prov:entity": "rdt:d10",
			"prov:activity": "rdt:p7"
		},
		"rdt:dp11": {
			"prov:entity": "rdt:d11",
			"prov:activity": "rdt:p7"
		},
		"rdt:dp12": {
			"prov:entity": "rdt:d12",
			"prov:activity": "rdt:p7"
		},
		"rdt:dp13": {
			"prov:entity": "rdt:d13",
			"prov:activity": "rdt:p7"
		},
		"rdt:dp14": {
			"prov:entity": "rdt:d14",
			"prov:activity": "rdt:p7"
		},
		"rdt:dp15": {
			"prov:entity": "rdt:d15",
			"prov:activity": "rdt:p7"
		},
		"rdt:dp16": {
			"prov:entity": "rdt:d16",
			"prov:activity": "rdt:p7"
		},
		"rdt:dp17": {
			"prov:entity": "rdt:d17",
			"prov:activity": "rdt:p7"
		},
		"rdt:dp18": {
			"prov:entity": "rdt:d18",
			"prov:activity": "rdt:p7"
		},
		"rdt:dp19": {
			"prov:entity": "rdt:d19",
			"prov:activity": "rdt:p7"
		},
		"rdt:dp20": {
			"prov:entity": "rdt:d20",
			"prov:activity": "rdt:p7"
		},
		"rdt:dp21": {
			"prov:entity": "rdt:d21",
			"prov:activity": "rdt:p7"
		},
		"rdt:dp22": {
			"prov:entity": "rdt:d22",
			"prov:activity": "rdt:p7"
		},
		"rdt:dp23": {
			"prov:entity": "rdt:d23",
			"prov:activity": "rdt:p7"
		},
		"rdt:dp24": {
			"prov:entity": "rdt:d24",
			"prov:activity": "rdt:p7"
		},
		"rdt:dp25": {
			"prov:entity": "rdt:d25",
			"prov:activity": "rdt:p7"
		},
		"rdt:dp26": {
			"prov:entity": "rdt:d26",
			"prov:activity": "rdt:p7"
		},
		"rdt:dp27": {
			"prov:entity": "rdt:d27",
			"prov:activity": "rdt:p7"
		},
		"rdt:dp28": {
			"prov:entity": "rdt:d28",
			"prov:activity": "rdt:p7"
		},
		"rdt:dp29": {
			"prov:entity": "rdt:d29",
			"prov:activity": "rdt:p7"
		},
		"rdt:dp30": {
			"prov:entity": "rdt:d30",
			"prov:activity": "rdt:p7"
		},
		"rdt:dp31": {
			"prov:entity": "rdt:d31",
			"prov:activity": "rdt:p7"
		},
		"rdt:dp32": {
			"prov:entity": "rdt:d32",
			"prov:activity": "rdt:p7"
		},
		"rdt:dp33": {
			"prov:entity": "rdt:d33",
			"prov:activity": "rdt:p7"
		},
		"rdt:dp34": {
			"prov:entity": "rdt:d34",
			"prov:activity": "rdt:p7"
		},
		"rdt:dp35": {
			"prov:entity": "rdt:d35",
			"prov:activity": "rdt:p7"
		},
		"rdt:dp36": {
			"prov:entity": "rdt:d36",
			"prov:activity": "rdt:p7"
		},
		"rdt:dp37": {
			"prov:entity": "rdt:d37",
			"prov:activity": "rdt:p7"
		},
		"rdt:dp38": {
			"prov:entity": "rdt:d38",
			"prov:activity": "rdt:p7"
		},
		"rdt:dp39": {
			"prov:entity": "rdt:d39",
			"prov:activity": "rdt:p7"
		},
		"rdt:dp40": {
			"prov:entity": "rdt:d40",
			"prov:activity": "rdt:p7"
		},
		"rdt:dp41": {
			"prov:entity": "rdt:d41",
			"prov:activity": "rdt:p7"
		},
		"rdt:dp42": {
			"prov:entity": "rdt:d42",
			"prov:activity": "rdt:p7"
		},
		"rdt:dp43": {
			"prov:entity": "rdt:d43",
			"prov:activity": "rdt:p7"
		},
		"rdt:dp44": {
			"prov:entity": "rdt:d44",
			"prov:activity": "rdt:p7"
		},
		"rdt:dp45": {
			"prov:entity": "rdt:d45",
			"prov:activity": "rdt:p7"
		},
		"rdt:dp46": {
			"prov:entity": "rdt:d46",
			"prov:activity": "rdt:p7"
		},
		"rdt:dp47": {
			"prov:entity": "rdt:d47",
			"prov:activity": "rdt:p7"
		},
		"rdt:dp48": {
			"prov:entity": "rdt:d48",
			"prov:activity": "rdt:p7"
		},
		"rdt:dp49": {
			"prov:entity": "rdt:d49",
			"prov:activity": "rdt:p7"
		},
		"rdt:dp50": {
			"prov:entity": "rdt:d50",
			"prov:activity": "rdt:p7"
		},
		"rdt:dp51": {
			"prov:entity": "rdt:d51",
			"prov:activity": "rdt:p7"
		},
		"rdt:dp52": {
			"prov:entity": "rdt:d52",
			"prov:activity": "rdt:p7"
		},
		"rdt:dp53": {
			"prov:entity": "rdt:d53",
			"prov:activity": "rdt:p7"
		},
		"rdt:dp54": {
			"prov:entity": "rdt:d54",
			"prov:activity": "rdt:p7"
		},
		"rdt:dp55": {
			"prov:entity": "rdt:d55",
			"prov:activity": "rdt:p7"
		},
		"rdt:dp56": {
			"prov:entity": "rdt:d56",
			"prov:activity": "rdt:p7"
		},
		"rdt:dp57": {
			"prov:entity": "rdt:d57",
			"prov:activity": "rdt:p7"
		},
		"rdt:dp58": {
			"prov:entity": "rdt:d58",
			"prov:activity": "rdt:p7"
		},
		"rdt:dp59": {
			"prov:entity": "rdt:d59",
			"prov:activity": "rdt:p7"
		},
		"rdt:dp60": {
			"prov:entity": "rdt:d60",
			"prov:activity": "rdt:p7"
		},
		"rdt:dp61": {
			"prov:entity": "rdt:d61",
			"prov:activity": "rdt:p7"
		},
		"rdt:dp62": {
			"prov:entity": "rdt:d62",
			"prov:activity": "rdt:p7"
		},
		"rdt:dp63": {
			"prov:entity": "rdt:d63",
			"prov:activity": "rdt:p7"
		},
		"rdt:dp64": {
			"prov:entity": "rdt:d64",
			"prov:activity": "rdt:p7"
		},
		"rdt:dp65": {
			"prov:entity": "rdt:d65",
			"prov:activity": "rdt:p7"
		},
		"rdt:dp66": {
			"prov:entity": "rdt:d66",
			"prov:activity": "rdt:p7"
		},
		"rdt:dp67": {
			"prov:entity": "rdt:d67",
			"prov:activity": "rdt:p7"
		},
		"rdt:dp68": {
			"prov:entity": "rdt:d68",
			"prov:activity": "rdt:p7"
		},
		"rdt:dp69": {
			"prov:entity": "rdt:d69",
			"prov:activity": "rdt:p7"
		},
		"rdt:dp70": {
			"prov:entity": "rdt:d70",
			"prov:activity": "rdt:p7"
		},
		"rdt:dp71": {
			"prov:entity": "rdt:d71",
			"prov:activity": "rdt:p7"
		},
		"rdt:dp72": {
			"prov:entity": "rdt:d72",
			"prov:activity": "rdt:p7"
		},
		"rdt:dp73": {
			"prov:entity": "rdt:d73",
			"prov:activity": "rdt:p7"
		},
		"rdt:dp74": {
			"prov:entity": "rdt:d1",
			"prov:activity": "rdt:p8"
		},
		"rdt:dp75": {
			"prov:entity": "rdt:d3",
			"prov:activity": "rdt:p8"
		},
		"rdt:dp76": {
			"prov:entity": "rdt:d73",
			"prov:activity": "rdt:p8"
		},
		"rdt:dp77": {
			"prov:entity": "rdt:d78",
			"prov:activity": "rdt:p8"
		},
		"rdt:dp78": {
			"prov:entity": "rdt:d79",
			"prov:activity": "rdt:p8"
		},
		"rdt:dp79": {
			"prov:entity": "rdt:d80",
			"prov:activity": "rdt:p8"
		},
		"rdt:dp80": {
			"prov:entity": "rdt:d81",
			"prov:activity": "rdt:p8"
		},
		"rdt:dp81": {
			"prov:entity": "rdt:d82",
			"prov:activity": "rdt:p8"
		},
		"rdt:dp82": {
			"prov:entity": "rdt:d83",
			"prov:activity": "rdt:p8"
		},
		"rdt:dp83": {
			"prov:entity": "rdt:d84",
			"prov:activity": "rdt:p8"
		},
		"rdt:dp84": {
			"prov:entity": "rdt:d85",
			"prov:activity": "rdt:p8"
		},
		"rdt:dp85": {
			"prov:entity": "rdt:d86",
			"prov:activity": "rdt:p8"
		},
		"rdt:dp86": {
			"prov:entity": "rdt:d87",
			"prov:activity": "rdt:p8"
		},
		"rdt:dp87": {
			"prov:entity": "rdt:d88",
			"prov:activity": "rdt:p8"
		},
		"rdt:dp88": {
			"prov:entity": "rdt:d89",
			"prov:activity": "rdt:p8"
		},
		"rdt:dp89": {
			"prov:entity": "rdt:d90",
			"prov:activity": "rdt:p8"
		},
		"rdt:dp90": {
			"prov:entity": "rdt:d91",
			"prov:activity": "rdt:p8"
		},
		"rdt:dp91": {
			"prov:entity": "rdt:d92",
			"prov:activity": "rdt:p8"
		},
		"rdt:dp92": {
			"prov:entity": "rdt:d93",
			"prov:activity": "rdt:p8"
		},
		"rdt:dp93": {
			"prov:entity": "rdt:d94",
			"prov:activity": "rdt:p8"
		},
		"rdt:dp94": {
			"prov:entity": "rdt:d95",
			"prov:activity": "rdt:p8"
		},
		"rdt:dp95": {
			"prov:entity": "rdt:d96",
			"prov:activity": "rdt:p8"
		},
		"rdt:dp96": {
			"prov:entity": "rdt:d97",
			"prov:activity": "rdt:p8"
		},
		"rdt:dp97": {
			"prov:entity": "rdt:d98",
			"prov:activity": "rdt:p8"
		},
		"rdt:dp98": {
			"prov:entity": "rdt:d99",
			"prov:activity": "rdt:p8"
		},
		"rdt:dp99": {
			"prov:entity": "rdt:d100",
			"prov:activity": "rdt:p8"
		},
		"rdt:dp100": {
			"prov:entity": "rdt:d101",
			"prov:activity": "rdt:p8"
		},
		"rdt:dp101": {
			"prov:entity": "rdt:d102",
			"prov:activity": "rdt:p8"
		},
		"rdt:dp102": {
			"prov:entity": "rdt:d103",
			"prov:activity": "rdt:p8"
		},
		"rdt:dp103": {
			"prov:entity": "rdt:d77",
			"prov:activity": "rdt:p8"
		},
		"rdt:dp104": {
			"prov:entity": "rdt:d1",
			"prov:activity": "rdt:p9"
		},
		"rdt:dp105": {
			"prov:entity": "rdt:d3",
			"prov:activity": "rdt:p9"
		},
		"rdt:dp106": {
			"prov:entity": "rdt:d113",
			"prov:activity": "rdt:p9"
		},
		"rdt:dp107": {
			"prov:entity": "rdt:d110",
			"prov:activity": "rdt:p9"
		},
		"rdt:dp108": {
			"prov:entity": "rdt:d107",
			"prov:activity": "rdt:p9"
		},
		"rdt:dp109": {
			"prov:entity": "rdt:d116",
			"prov:activity": "rdt:p9"
		},
		"rdt:dp110": {
			"prov:entity": "rdt:d119",
			"prov:activity": "rdt:p9"
		},
		"rdt:dp111": {
			"prov:entity": "rdt:d103",
			"prov:activity": "rdt:p9"
		},
		"rdt:dp112": {
			"prov:entity": "rdt:d121",
			"prov:activity": "rdt:p9"
		},
		"rdt:dp113": {
			"prov:entity": "rdt:d1",
			"prov:activity": "rdt:p10"
		},
		"rdt:dp114": {
			"prov:entity": "rdt:d2",
			"prov:activity": "rdt:p10"
		},
		"rdt:dp115": {
			"prov:entity": "rdt:d3",
			"prov:activity": "rdt:p10"
		},
		"rdt:dp116": {
			"prov:entity": "rdt:d124",
			"prov:activity": "rdt:p10"
		},
		"rdt:dp117": {
			"prov:entity": "rdt:d121",
			"prov:activity": "rdt:p10"
		},

		"rdt:fp1": {
			"prov:entity": "rdt:f1",
			"prov:activity": "rdt:p7"
		},
		"rdt:fp2": {
			"prov:entity": "rdt:f2",
			"prov:activity": "rdt:p8"
		},
		"rdt:fp3": {
			"prov:entity": "rdt:f3",
			"prov:activity": "rdt:p9"
		},
		"rdt:fp4": {
			"prov:entity": "rdt:f4",
			"prov:activity": "rdt:p10"
		}
	},

	"hadMember" : {
		"rdt:m1": {
			"prov:collection": "rdt:l8",
			"prov:entity": "rdt:f1"
		},
		"rdt:m2": {
			"prov:collection": "rdt:l8",
			"prov:entity": "rdt:f2"
		},
		"rdt:m3": {
			"prov:collection": "rdt:l8",
			"prov:entity": "rdt:f3"
		},
		"rdt:m4": {
			"prov:collection": "rdt:l8",
			"prov:entity": "rdt:f4"
		}
	}
}
